Workbook

Sheet Source
A1: OrderNbr | B1: Customer | C1: CustomerName | D1: Date | E1: OrderTotal | F1: CreatedBy
A2: SO00000687 | B2: 1250000116 | C2: CITY GOVERNMENT OF DAVAO | D2: 45250 | E2: ₱4372.25 | F2: GRACE POLPOL
A3: SO00000012 | B3: 1250000505 | C3: STAR PAPER CORPORATION | D3: 45294 | E3: ₱1362.00 | F3: ANGELI SUMINGIT
A4: SO00000005 | B4: 1250001764 | C4: STENIEL MINDANAO PACKAGING CORPORATION | D4: 45294 | E4: ₱1500.00 | F4: ANGELI SUMINGIT
A5: SO00000028 | B5: 1250001496 | C5: COMFAC CORPORATION | D5: 45294 | E5: ₱1916.00 | F5: ANGELI SUMINGIT
A6: SO00000021 | B6: 1200006565 | C6: NXTGEN TECHNOLOGIES INC | D6: 45294 | E6: ₱2148.80 | F6: ANGELI SUMINGIT
A7: SO00000026 | B7: 1250004966 | C7: INFIMAX HEALTH PRODUCTS | D7: 45294 | E7: ₱2365.80 | F7: ANGELI SUMINGIT
A8: SO00000020 | B8: 1250001764 | C8: STENIEL MINDANAO PACKAGING CORPORATION | D8: 45294 | E8: ₱2367.50 | F8: ANGELI SUMINGIT
A9: SO00000013 | B9: 1250001142 | C9: DEPT. OF HUMAN SETTLEMENTS & URBAN DEV'T | D9: 45294 | E9: ₱38256.00 | F9: GRACE POLPOL
A10: SO00000097 | B10: 1200006417 | C10: PHIL.FIBER INDUSTRY DEV'T AUTHORITY | D10: 45295 | E10: ₱1500.00 | F10: GRACE POLPOL
A11: SO00000071 | B11: 1250010315 | C11: HI5 SOLUTIONS OPC | D11: 45295 | E11: ₱1600.00 | F11: ANGELI SUMINGIT
A12: SO00000096 | B12: 1250004938 | C12: B.P.I. - BAJADA (FRONTING CONPINCO) | D12: 45295 | E12: ₱4762.10 | F12: ANGELI SUMINGIT
A13: SO00000070 | B13: 1250003997 | C13: INSULAR OIL CORPORATION | D13: 45295 | E13: ₱5265.00 | F13: ANGELI SUMINGIT
... A201: SO00001324 | B201: 1250001273 | C201: MILLENNIUM SPECIALTY COCO PRODUCTSINC. | D201: 45337 | E201: ₱1200.00 | F201: ANGELI SUMINGIT

Sheet Rhea
A1: OrderNbr | B1: Customer | C1: CustomerName | D1: Date | E1: OrderTotal | F1: CreatedBy
A2: SO00000687 | B2: 1250000116 | C2: CITY GOVERNMENT OF DAVAO | D2: 45250 | E2: 4372.25 | F2: GRACE POLPOL
A3: SO00000012 | B3: 1250000505 | C3: STAR PAPER CORPORATION | D3: 45294 | E3: 1362 | F3: ANGELI SUMINGIT
A4: SO00000005 | B4: 1250001764 | C4: STENIEL MINDANAO PACKAGING CORPORATION | D4: 45294 | E4: 1500 | F4: ANGELI SUMINGIT
A5: SO00000028 | B5: 1250001496 | C5: COMFAC CORPORATION | D5: 45294 | E5: 1916 | F5: ANGELI SUMINGIT
A6: SO00000021 | B6: 1200006565 | C6: NXTGEN TECHNOLOGIES INC | D6: 45294 | E6: 2148.8 | F6: ANGELI SUMINGIT
A7: SO00000026 | B7: 1250004966 | C7: INFIMAX HEALTH PRODUCTS | D7: 45294 | E7: 2365.8 | F7: ANGELI SUMINGIT
A8: SO00000020 | B8: 1250001764 | C8: STENIEL MINDANAO PACKAGING CORPORATION | D8: 45294 | E8: 2367.5 | F8: ANGELI SUMINGIT
A9: SO00000013 | B9: 1250001142 | C9: DEPT. OF HUMAN SETTLEMENTS & URBAN DEV'T | D9: 45294 | E9: 38256 | F9: GRACE POLPOL
A10: SO00000097 | B10: 1200006417 | C10: PHIL.FIBER INDUSTRY DEV'T AUTHORITY | D10: 45295 | E10: 1500 | F10: GRACE POLPOL
A11: SO00000071 | B11: 1250010315 | C11: HI5 SOLUTIONS OPC | D11: 45295 | E11: 1600 | F11: ANGELI SUMINGIT
A12: SO00000096 | B12: 1250004938 | C12: B.P.I. - BAJADA (FRONTING CONPINCO) | D12: 45295 | E12: 4762.1 | F12: ANGELI SUMINGIT
A13: SO00000070 | B13: 1250003997 | C13: INSULAR OIL CORPORATION | D13: 45295 | E13: 5265 | F13: ANGELI SUMINGIT
... A201: SO00001324 | B201: 1250001273 | C201: MILLENNIUM SPECIALTY COCO PRODUCTSINC. | D201: 45337 | E201: 1200 | F201: ANGELI SUMINGIT

Sheet rhea_rhea
B122: =SUMIF(Rhea!D2:D1000,A122,Rhea!E:E) -> 0
B123: =SUMIF(Rhea!D3:D1000,A123,Rhea!E:E) -> 0
B124: =SUMIF(Rhea!D4:D1000,A124,Rhea!E:E) -> 0
B125: =SUMIF(Rhea!D5:D1000,A125,Rhea!E:E) -> 0
B126: =SUMIF(Rhea!D6:D1000,A126,Rhea!E:E) -> 0
B127: =SUMIF(Rhea!D7:D1000,A127,Rhea!E:E) -> 0
B128: =SUMIF(Rhea!D8:D1000,A128,Rhea!E:E) -> 0
B129: =SUMIF(Rhea!D9:D1000,A129,Rhea!E:E) -> 0
B130: =SUMIF(Rhea!D10:D1000,A130,Rhea!E:E) -> 0
B131: =SUMIF(Rhea!D11:D1000,A131,Rhea!E:E) -> 0
B132: =SUMIF(Rhea!D12:D1000,A132,Rhea!E:E) -> 0
B133: =SUMIF(Rhea!D13:D1000,A133,Rhea!E:E) -> 0
B134: =SUMIF(Rhea!D14:D1000,A134,Rhea!E:E) -> 0
B135: =SUMIF(Rhea!D15:D1000,A135,Rhea!E:E) -> 0
B136: =SUMIF(Rhea!D16:D1000,A136,Rhea!E:E) -> 0
B137: =SUMIF(Rhea!D17:D1000,A137,Rhea!E:E) -> 0
B138: =SUMIF(Rhea!D18:D1000,A138,Rhea!E:E) -> 0
B139: =SUMIF(Rhea!D19:D1000,A139,Rhea!E:E) -> 0
B140: =SUMIF(Rhea!D20:D1000,A140,Rhea!E:E) -> 0
B141: =SUMIF(Rhea!D21:D1000,A141,Rhea!E:E) -> 0
B142: =SUMIF(Rhea!D22:D1000,A142,Rhea!E:E) -> 0
B143: =SUMIF(Rhea!D23:D1000,A143,Rhea!E:E) -> 0
B144: =SUMIF(Rhea!D24:D1000,A144,Rhea!E:E) -> 0
B145: =SUMIF(Rhea!D25:D1000,A145,Rhea!E:E) -> 0
B146: =SUMIF(Rhea!D26:D1000,A146,Rhea!E:E) -> 0
B147: =SUMIF(Rhea!D27:D1000,A147,Rhea!E:E) -> 0
B148: =SUMIF(Rhea!D28:D1000,A148,Rhea!E:E) -> 0
B149: =SUMIF(Rhea!D29:D1000,A149,Rhea!E:E) -> 0
B150: =SUMIF(Rhea!D30:D1000,A150,Rhea!E:E) -> 0
B151: =SUMIF(Rhea!D31:D1000,A151,Rhea!E:E) -> 0
B152: =SUMIF(Rhea!D32:D1000,A152,Rhea!E:E) -> 0
B153: =SUMIF(Rhea!D33:D1000,A153,Rhea!E:E) -> 0
B154: =SUMIF(Rhea!D34:D1000,A154,Rhea!E:E) -> 0
B155: =SUMIF(Rhea!D35:D1000,A155,Rhea!E:E) -> 0
B156: =SUMIF(Rhea!D36:D1000,A156,Rhea!E:E) -> 0
B157: =SUMIF(Rhea!D37:D1000,A157,Rhea!E:E) -> 0

Sheet John 1
B23: amounting to | C23: 0.54977723 | D23: total | E23: 1455920.9 | G23: avaergae number pf transaction per month | H23: 1.4936709 | I23: jan
C24: =C23*100 -> 54.977723 | D24: ot the sales | H24: 1.7608696 | I24: feb

Sheet Copy of John 1
A1: OrderNbr | B1: Customer | C1: CustomerName | D1: Date | E1: OrderTotal | F1: CreatedBy | K1: CustomerName | L1: month | M1: OrderTotal | R1: =IFERROR(__xludf.DUMMYFUNCTION("QUERY('Copy of John 1'!C:E, ""SELECT C, SUM(E) WHERE C IS NOT NULL GROUP BY C ORDER BY SUM(E) DESC LIMIT 5"", 1)"),"CustomerName") -> CustomerName | S1: =IFERROR(__xludf.DUMMYFUNCTION("""COMPUTED_VALUE"""),"sum OrderTotal") -> sum OrderTotal | U1: CustomerName | V1: count OrderTotal | AT1: =IFERROR(__xludf.DUMMYFUNCTION("QUERY(AH2:AJ239, ""SELECT AH, AJ WHERE AI > 0 ORDER BY AH DESC"", 1)"),"AFP & POLICE SAVINGS LOAN ASSN (AFPSLAI)") -> AFP & POLICE SAVINGS LOAN ASSN (AFPSLAI) | AU1: =IFERROR(__xludf.DUMMYFUNCTION("""COMPUTED_VALUE"""),"1") -> 1
A2: SO00000687 | B2: 1250000116.00 | C2: CITY GOVERNMENT OF DAVAO | D2: 45250 | E2: 4372.25 | F2: GRACE POLPOL | K2: CITY GOVERNMENT OF DAVAO | L2: {=text(D2:D201,"mmmm")} -> November | M2: 4372.25 | R2: =IFERROR(__xludf.DUMMYFUNCTION("""COMPUTED_VALUE"""),"MUNICIPALITY OF LUPON - LGU") -> MUNICIPALITY OF LUPON - LGU | S2: =IFERROR(__xludf.DUMMYFUNCTION("""COMPUTED_VALUE"""),636382.0) -> 636382 | U2: MUNICIPALITY OF LUPON - LGU | V2: 21 | AL2: =IFERROR(__xludf.DUMMYFUNCTION("QUERY(AH1:AJ1000)"),"CustomerName") -> CustomerName | AM2: =IFERROR(__xludf.DUMMYFUNCTION("""COMPUTED_VALUE"""),"month") -> month | AN2: =IFERROR(__xludf.DUMMYFUNCTION("""COMPUTED_VALUE"""),"COUNTA of month") -> COUNTA of month | AP2: =IFERROR(__xludf.DUMMYFUNCTION("QUERY(AH1:AJ239)"),"CustomerName") -> CustomerName | AQ2: =IFERROR(__xludf.DUMMYFUNCTION("""COMPUTED_VALUE"""),"month") -> month | AR2: =IFERROR(__xludf.DUMMYFUNCTION("""COMPUTED_VALUE"""),"COUNTA of month") -> COUNTA of month
A3: SO00000012 | B3: 1250000505.00 | C3: STAR PAPER CORPORATION | D3: 45294 | E3: 1362 | F3: ANGELI SUMINGIT | K3: STAR PAPER CORPORATION | L3: January | M3: 1362 | R3: =IFERROR(__xludf.DUMMYFUNCTION("""COMPUTED_VALUE"""),"AMERICARES FOUNDATION INC.") -> AMERICARES FOUNDATION INC. | S3: =IFERROR(__xludf.DUMMYFUNCTION("""COMPUTED_VALUE"""),365925.0) -> 365925 | U3: STENIEL MINDANAO PACKAGING CORPORATION | V3: 14 | AL3: =IFERROR(__xludf.DUMMYFUNCTION("""COMPUTED_VALUE"""),"AFP & POLICE SAVINGS LOAN ASSN (AFPSLAI)") -> AFP & POLICE SAVINGS LOAN ASSN (AFPSLAI) | AM3: =IFERROR(__xludf.DUMMYFUNCTION("""COMPUTED_VALUE"""),"February") -> February | AN3: =IFERROR(__xludf.DUMMYFUNCTION("""COMPUTED_VALUE"""),1.0) -> 1 | AP3: =IFERROR(__xludf.DUMMYFUNCTION("""COMPUTED_VALUE"""),"AFP & POLICE SAVINGS LOAN ASSN (AFPSLAI)") -> AFP & POLICE SAVINGS LOAN ASSN (AFPSLAI) | AQ3: =IFERROR(__xludf.DUMMYFUNCTION("""COMPUTED_VALUE"""),"February") -> February | AR3: =IFERROR(__xludf.DUMMYFUNCTION("""COMPUTED_VALUE"""),1.0) -> 1 | AT3: =IFERROR(__xludf.DUMMYFUNCTION("QUERY('Copy of John 1'!K1:M201, ""SELECT K, COUNT(M) WHERE K IS NOT NULL GROUP BY K ORDER BY COUNT(M) DESC LIMIT 5"", 1)"),"CustomerName") -> CustomerName | AU3: =IFERROR(__xludf.DUMMYFUNCTION("""COMPUTED_VALUE"""),"count OrderTotal") -> count OrderTotal
A4: SO00000005 | B4: 1250001764.00 | C4: STENIEL MINDANAO PACKAGING CORPORATION | D4: 45294 | E4: 1500 | F4: ANGELI SUMINGIT | K4: STENIEL MINDANAO PACKAGING CORPORATION | L4: January | M4: 1500 | R4: =IFERROR(__xludf.DUMMYFUNCTION("""COMPUTED_VALUE"""),"STENIEL MINDANAO PACKAGING CORPORATION") -> STENIEL MINDANAO PACKAGING CORPORATION | S4: =IFERROR(__xludf.DUMMYFUNCTION("""COMPUTED_VALUE"""),248363.5) -> 248363.5 | U4: CIVIL SERVICE COMMISSION-REG. XI | V4: 6 | AL4: =IFERROR(__xludf.DUMMYFUNCTION("""COMPUTED_VALUE"""),"AFP & POLICE SAVINGS LOAN ASSN (AFPSLAI) Total") -> AFP & POLICE SAVINGS LOAN ASSN (AFPSLAI) Total | AN4: =IFERROR(__xludf.DUMMYFUNCTION("""COMPUTED_VALUE"""),1.0) -> 1 | AP4: =IFERROR(__xludf.DUMMYFUNCTION("""COMPUTED_VALUE"""),"AFP & POLICE SAVINGS LOAN ASSN (AFPSLAI) Total") -> AFP & POLICE SAVINGS LOAN ASSN (AFPSLAI) Total | AR4: =IFERROR(__xludf.DUMMYFUNCTION("""COMPUTED_VALUE"""),1.0) -> 1 | AT4: =IFERROR(__xludf.DUMMYFUNCTION("""COMPUTED_VALUE"""),"MUNICIPALITY OF LUPON - LGU") -> MUNICIPALITY OF LUPON - LGU | AU4: =IFERROR(__xludf.DUMMYFUNCTION("""COMPUTED_VALUE"""),21.0) -> 21
A5: SO00000028 | B5: 1250001496.00 | C5: COMFAC CORPORATION | D5: 45294 | E5: 4372.25 | F5: ANGELI SUMINGIT | K5: COMFAC CORPORATION | L5: January | M5: 4372.25 | R5: =IFERROR(__xludf.DUMMYFUNCTION("""COMPUTED_VALUE"""),"DEPT. OF HUMAN SETTLEMENTS & URBAN DEV'T") -> DEPT. OF HUMAN SETTLEMENTS & URBAN DEV'T | S5: =IFERROR(__xludf.DUMMYFUNCTION("""COMPUTED_VALUE"""),146676.0) -> 146676 | U5: EC GONZAGA ENTERPRISES | V5: 6 | AL5: =IFERROR(__xludf.DUMMYFUNCTION("""COMPUTED_VALUE"""),"AGRI DAVAO INCORPORATED") -> AGRI DAVAO INCORPORATED | AM5: =IFERROR(__xludf.DUMMYFUNCTION("""COMPUTED_VALUE"""),"February") -> February | AN5: =IFERROR(__xludf.DUMMYFUNCTION("""COMPUTED_VALUE"""),1.0) -> 1 | AP5: =IFERROR(__xludf.DUMMYFUNCTION("""COMPUTED_VALUE"""),"AGRI DAVAO INCORPORATED") -> AGRI DAVAO INCORPORATED | AQ5: =IFERROR(__xludf.DUMMYFUNCTION("""COMPUTED_VALUE"""),"February") -> February | AR5: =IFERROR(__xludf.DUMMYFUNCTION("""COMPUTED_VALUE"""),1.0) -> 1 | AT5: =IFERROR(__xludf.DUMMYFUNCTION("""COMPUTED_VALUE"""),"STENIEL MINDANAO PACKAGING CORPORATION") -> STENIEL MINDANAO PACKAGING CORPORATION | AU5: =IFERROR(__xludf.DUMMYFUNCTION("""COMPUTED_VALUE"""),14.0) -> 14
A6: SO00000021 | B6: 1200006565.00 | C6: NXTGEN TECHNOLOGIES INC | D6: 45294 | E6: 2148.8 | F6: ANGELI SUMINGIT | K6: NXTGEN TECHNOLOGIES INC | L6: January | M6: 2148.8 | R6: =IFERROR(__xludf.DUMMYFUNCTION("""COMPUTED_VALUE"""),"EC GONZAGA ENTERPRISES") -> EC GONZAGA ENTERPRISES | S6: =IFERROR(__xludf.DUMMYFUNCTION("""COMPUTED_VALUE"""),58574.45) -> 58574.45 | U6: ANTONIO'S GRILL | V6: 5 | AM6: =IFERROR(__xludf.DUMMYFUNCTION("""COMPUTED_VALUE"""),"January") -> January | AN6: =IFERROR(__xludf.DUMMYFUNCTION("""COMPUTED_VALUE"""),1.0) -> 1 | AQ6: =IFERROR(__xludf.DUMMYFUNCTION("""COMPUTED_VALUE"""),"January") -> January | AR6: =IFERROR(__xludf.DUMMYFUNCTION("""COMPUTED_VALUE"""),1.0) -> 1 | AT6: =IFERROR(__xludf.DUMMYFUNCTION("""COMPUTED_VALUE"""),"CIVIL SERVICE COMMISSION-REG. XI") -> CIVIL SERVICE COMMISSION-REG. XI | AU6: =IFERROR(__xludf.DUMMYFUNCTION("""COMPUTED_VALUE"""),6.0) -> 6
A7: SO00000026 | B7: 1250004966.00 | C7: INFIMAX HEALTH PRODUCTS | D7: 45294 | E7: 2365.8 | F7: ANGELI SUMINGIT | K7: INFIMAX HEALTH PRODUCTS | L7: January | M7: 2365.8 | AL7: =IFERROR(__xludf.DUMMYFUNCTION("""COMPUTED_VALUE"""),"AGRI DAVAO INCORPORATED Total") -> AGRI DAVAO INCORPORATED Total | AN7: =IFERROR(__xludf.DUMMYFUNCTION("""COMPUTED_VALUE"""),2.0) -> 2 | AP7: =IFERROR(__xludf.DUMMYFUNCTION("""COMPUTED_VALUE"""),"AGRI DAVAO INCORPORATED Total") -> AGRI DAVAO INCORPORATED Total | AR7: =IFERROR(__xludf.DUMMYFUNCTION("""COMPUTED_VALUE"""),2.0) -> 2 | AT7: =IFERROR(__xludf.DUMMYFUNCTION("""COMPUTED_VALUE"""),"EC GONZAGA ENTERPRISES") -> EC GONZAGA ENTERPRISES | AU7: =IFERROR(__xludf.DUMMYFUNCTION("""COMPUTED_VALUE"""),6.0) -> 6
A8: SO00000020 | B8: 1250001764.00 | C8: STENIEL MINDANAO PACKAGING CORPORATION | D8: 45294 | E8: 2367.5 | F8: ANGELI SUMINGIT | K8: STENIEL MINDANAO PACKAGING CORPORATION | L8: January | M8: 2367.5 | T8: =sum(S2:S6) -> 1455920.9 | AL8: =IFERROR(__xludf.DUMMYFUNCTION("""COMPUTED_VALUE"""),"AKTIV MULTI TRADING CO. PHILS. INC.") -> AKTIV MULTI TRADING CO. PHILS. INC. | AM8: =IFERROR(__xludf.DUMMYFUNCTION("""COMPUTED_VALUE"""),"January") -> January | AN8: =IFERROR(__xludf.DUMMYFUNCTION("""COMPUTED_VALUE"""),1.0) -> 1 | AP8: =IFERROR(__xludf.DUMMYFUNCTION("""COMPUTED_VALUE"""),"AKTIV MULTI TRADING CO. PHILS. INC.") -> AKTIV MULTI TRADING CO. PHILS. INC. | AQ8: =IFERROR(__xludf.DUMMYFUNCTION("""COMPUTED_VALUE"""),"January") -> January | AR8: =IFERROR(__xludf.DUMMYFUNCTION("""COMPUTED_VALUE"""),1.0) -> 1 | AT8: =IFERROR(__xludf.DUMMYFUNCTION("""COMPUTED_VALUE"""),"ANTONIO'S GRILL") -> ANTONIO'S GRILL | AU8: =IFERROR(__xludf.DUMMYFUNCTION("""COMPUTED_VALUE"""),5.0) -> 5
A9: SO00000013 | B9: 1250001142.00 | C9: DEPT. OF HUMAN SETTLEMENTS & URBAN DEV'T | D9: 45294 | E9: 38256 | F9: GRACE POLPOL | K9: DEPT. OF HUMAN SETTLEMENTS & URBAN DEV'T | L9: January | M9: 38256 | AL9: =IFERROR(__xludf.DUMMYFUNCTION("""COMPUTED_VALUE"""),"AKTIV MULTI TRADING CO. PHILS. INC. Total") -> AKTIV MULTI TRADING CO. PHILS. INC. Total | AN9: =IFERROR(__xludf.DUMMYFUNCTION("""COMPUTED_VALUE"""),1.0) -> 1 | AP9: =IFERROR(__xludf.DUMMYFUNCTION("""COMPUTED_VALUE"""),"AKTIV MULTI TRADING CO. PHILS. INC. Total") -> AKTIV MULTI TRADING CO. PHILS. INC. Total | AR9: =IFERROR(__xludf.DUMMYFUNCTION("""COMPUTED_VALUE"""),1.0) -> 1
A10: SO00000097 | B10: 1200006417.00 | C10: PHIL.FIBER INDUSTRY DEV'T AUTHORITY | D10: 45295 | E10: 1500 | F10: GRACE POLPOL | K10: PHIL.FIBER INDUSTRY DEV'T AUTHORITY | L10: January | M10: 1500 | AL10: =IFERROR(__xludf.DUMMYFUNCTION("""COMPUTED_VALUE"""),"AMALGATED CAPITAL INCORPORATED") -> AMALGATED CAPITAL INCORPORATED | AM10: =IFERROR(__xludf.DUMMYFUNCTION("""COMPUTED_VALUE"""),"February") -> February | AN10: =IFERROR(__xludf.DUMMYFUNCTION("""COMPUTED_VALUE"""),3.0) -> 3 | AP10: =IFERROR(__xludf.DUMMYFUNCTION("""COMPUTED_VALUE"""),"AMALGATED CAPITAL INCORPORATED") -> AMALGATED CAPITAL INCORPORATED | AQ10: =IFERROR(__xludf.DUMMYFUNCTION("""COMPUTED_VALUE"""),"February") -> February | AR10: =IFERROR(__xludf.DUMMYFUNCTION("""COMPUTED_VALUE"""),3.0) -> 3 | AT10: =IFERROR(__xludf.DUMMYFUNCTION("QUERY('Copy of John 1'!K1:M201, ""SELECT K, COUNT(M) WHERE K IS NOT NULL AND L = 'January' GROUP BY K ORDER BY COUNT(M) DESC LIMIT 5"", 1)"),"CustomerName") -> CustomerName | AU10: =IFERROR(__xludf.DUMMYFUNCTION("""COMPUTED_VALUE"""),"count OrderTotal") -> count OrderTotal
A11: SO00000071 | B11: 1250010315.00 | C11: HI5 SOLUTIONS OPC | D11: 45295 | E11: 1600 | F11: ANGELI SUMINGIT | K11: HI5 SOLUTIONS OPC | L11: January | M11: 1600 | AL11: =IFERROR(__xludf.DUMMYFUNCTION("""COMPUTED_VALUE"""),"AMALGATED CAPITAL INCORPORATED Total") -> AMALGATED CAPITAL INCORPORATED Total | AN11: =IFERROR(__xludf.DUMMYFUNCTION("""COMPUTED_VALUE"""),3.0) -> 3 | AP11: =IFERROR(__xludf.DUMMYFUNCTION("""COMPUTED_VALUE"""),"AMALGATED CAPITAL INCORPORATED Total") -> AMALGATED CAPITAL INCORPORATED Total | AR11: =IFERROR(__xludf.DUMMYFUNCTION("""COMPUTED_VALUE"""),3.0) -> 3 | AT11: =IFERROR(__xludf.DUMMYFUNCTION("""COMPUTED_VALUE"""),"STENIEL MINDANAO PACKAGING CORPORATION") -> STENIEL MINDANAO PACKAGING CORPORATION | AU11: =IFERROR(__xludf.DUMMYFUNCTION("""COMPUTED_VALUE"""),9.0) -> 9
A12: SO00000096 | B12: 1250004938.00 | C12: B.P.I. - BAJADA (FRONTING CONPINCO) | D12: 45295 | E12: 4762.1 | F12: ANGELI SUMINGIT | K12: B.P.I. - BAJADA (FRONTING CONPINCO) | L12: January | M12: 4762.1 | AL12: =IFERROR(__xludf.DUMMYFUNCTION("""COMPUTED_VALUE"""),"AMERICARES FOUNDATION INC.") -> AMERICARES FOUNDATION INC. | AM12: =IFERROR(__xludf.DUMMYFUNCTION("""COMPUTED_VALUE"""),"January") -> January | AN12: =IFERROR(__xludf.DUMMYFUNCTION("""COMPUTED_VALUE"""),1.0) -> 1 | AP12: =IFERROR(__xludf.DUMMYFUNCTION("""COMPUTED_VALUE"""),"AMERICARES FOUNDATION INC.") -> AMERICARES FOUNDATION INC. | AQ12: =IFERROR(__xludf.DUMMYFUNCTION("""COMPUTED_VALUE"""),"January") -> January | AR12: =IFERROR(__xludf.DUMMYFUNCTION("""COMPUTED_VALUE"""),1.0) -> 1 | AT12: =IFERROR(__xludf.DUMMYFUNCTION("""COMPUTED_VALUE"""),"ANTONIO'S GRILL") -> ANTONIO'S GRILL | AU12: =IFERROR(__xludf.DUMMYFUNCTION("""COMPUTED_VALUE"""),5.0) -> 5
A13: SO00000070 | B13: 1250003997.00 | C13: INSULAR OIL CORPORATION | D13: 45295 | E13: 5265 | F13: ANGELI SUMINGIT | K13: INSULAR OIL CORPORATION | L13: January | M13: 5265 | AL13: =IFERROR(__xludf.DUMMYFUNCTION("""COMPUTED_VALUE"""),"AMERICARES FOUNDATION INC. Total") -> AMERICARES FOUNDATION INC. Total | AN13: =IFERROR(__xludf.DUMMYFUNCTION("""COMPUTED_VALUE"""),1.0) -> 1 | AP13: =IFERROR(__xludf.DUMMYFUNCTION("""COMPUTED_VALUE"""),"AMERICARES FOUNDATION INC. Total") -> AMERICARES FOUNDATION INC. Total | AR13: =IFERROR(__xludf.DUMMYFUNCTION("""COMPUTED_VALUE"""),1.0) -> 1 | AT13: =IFERROR(__xludf.DUMMYFUNCTION("""COMPUTED_VALUE"""),"CIVIL SERVICE COMMISSION-REG. XI") -> CIVIL SERVICE COMMISSION-REG. XI | AU13: =IFERROR(__xludf.DUMMYFUNCTION("""COMPUTED_VALUE"""),5.0) -> 5
A14: SO00000103 | B14: 1250003421.00 | C14: LAND BANK OF THE PHILS. - NABUNTURAN | D14: 45295 | E14: 51900 | F14: GRACE POLPOL | K14: LAND BANK OF THE PHILS. - NABUNTURAN | L14: January | M14: 51900 | AL14: =IFERROR(__xludf.DUMMYFUNCTION("""COMPUTED_VALUE"""),"AMESCO DRUG CORPORATION") -> AMESCO DRUG CORPORATION | AM14: =IFERROR(__xludf.DUMMYFUNCTION("""COMPUTED_VALUE"""),"February") -> February | AN14: =IFERROR(__xludf.DUMMYFUNCTION("""COMPUTED_VALUE"""),1.0) -> 1 | AP14: =IFERROR(__xludf.DUMMYFUNCTION("""COMPUTED_VALUE"""),"AMESCO DRUG CORPORATION") -> AMESCO DRUG CORPORATION | AQ14: =IFERROR(__xludf.DUMMYFUNCTION("""COMPUTED_VALUE"""),"February") -> February | AR14: =IFERROR(__xludf.DUMMYFUNCTION("""COMPUTED_VALUE"""),1.0) -> 1 | AT14: =IFERROR(__xludf.DUMMYFUNCTION("""COMPUTED_VALUE"""),"COMFAC CORPORATION") -> COMFAC CORPORATION | AU14: =IFERROR(__xludf.DUMMYFUNCTION("""COMPUTED_VALUE"""),4.0) -> 4
A15: SO00000146 | B15: 1200009067.00 | C15: IVN ENTERPRISES | D15: 45296 | E15: 2060 | F15: ANGELI SUMINGIT | K15: IVN ENTERPRISES | L15: January | M15: 2060 | AL15: =IFERROR(__xludf.DUMMYFUNCTION("""COMPUTED_VALUE"""),"AMESCO DRUG CORPORATION Total") -> AMESCO DRUG CORPORATION Total | AN15: =IFERROR(__xludf.DUMMYFUNCTION("""COMPUTED_VALUE"""),1.0) -> 1 | AP15: =IFERROR(__xludf.DUMMYFUNCTION("""COMPUTED_VALUE"""),"AMESCO DRUG CORPORATION Total") -> AMESCO DRUG CORPORATION Total | AR15: =IFERROR(__xludf.DUMMYFUNCTION("""COMPUTED_VALUE"""),1.0) -> 1 | AT15: =IFERROR(__xludf.DUMMYFUNCTION("""COMPUTED_VALUE"""),"DEPT. OF HUMAN SETTLEMENTS & URBAN DEV'T") -> DEPT. OF HUMAN SETTLEMENTS & URBAN DEV'T | AU15: =IFERROR(__xludf.DUMMYFUNCTION("""COMPUTED_VALUE"""),4.0) -> 4
A16: SO00000117 | B16: 1250000118.00 | C16: KIM GUAN TRADING CO. INC. | D16: 45296 | E16: 4097.5 | F16: ANGELI SUMINGIT | K16: KIM GUAN TRADING CO. INC. | L16: January | M16: 4097.5 | AL16: =IFERROR(__xludf.DUMMYFUNCTION("""COMPUTED_VALUE"""),"ANTONIO'S GRILL") -> ANTONIO'S GRILL | AM16: =IFERROR(__xludf.DUMMYFUNCTION("""COMPUTED_VALUE"""),"January") -> January | AN16: =IFERROR(__xludf.DUMMYFUNCTION("""COMPUTED_VALUE"""),5.0) -> 5 | AP16: =IFERROR(__xludf.DUMMYFUNCTION("""COMPUTED_VALUE"""),"ANTONIO'S GRILL") -> ANTONIO'S GRILL | AQ16: =IFERROR(__xludf.DUMMYFUNCTION("""COMPUTED_VALUE"""),"January") -> January | AR16: =IFERROR(__xludf.DUMMYFUNCTION("""COMPUTED_VALUE"""),5.0) -> 5
A17: SO00000124 | B17: 1250001741.00 | C17: SPAMAST | D17: 45296 | E17: 6230 | F17: GRACE POLPOL | K17: SPAMAST | L17: January | M17: 6230 | AL17: =IFERROR(__xludf.DUMMYFUNCTION("""COMPUTED_VALUE"""),"ANTONIO'S GRILL Total") -> ANTONIO'S GRILL Total | AN17: =IFERROR(__xludf.DUMMYFUNCTION("""COMPUTED_VALUE"""),5.0) -> 5 | AP17: =IFERROR(__xludf.DUMMYFUNCTION("""COMPUTED_VALUE"""),"ANTONIO'S GRILL Total") -> ANTONIO'S GRILL Total | AR17: =IFERROR(__xludf.DUMMYFUNCTION("""COMPUTED_VALUE"""),5.0) -> 5
A18: SO00000121 | B18: 1250001142.00 | C18: DEPT. OF HUMAN SETTLEMENTS & URBAN DEV'T | D18: 45296 | E18: 44970 | F18: GRACE POLPOL | K18: DEPT. OF HUMAN SETTLEMENTS & URBAN DEV'T | L18: January | M18: 44970 | AL18: =IFERROR(__xludf.DUMMYFUNCTION("""COMPUTED_VALUE"""),"ARM-G INT'L. LOGISTIC INC.") -> ARM-G INT'L. LOGISTIC INC. | AM18: =IFERROR(__xludf.DUMMYFUNCTION("""COMPUTED_VALUE"""),"January") -> January | AN18: =IFERROR(__xludf.DUMMYFUNCTION("""COMPUTED_VALUE"""),1.0) -> 1 | AP18: =IFERROR(__xludf.DUMMYFUNCTION("""COMPUTED_VALUE"""),"ARM-G INT'L. LOGISTIC INC.") -> ARM-G INT'L. LOGISTIC INC. | AQ18: =IFERROR(__xludf.DUMMYFUNCTION("""COMPUTED_VALUE"""),"January") -> January | AR18: =IFERROR(__xludf.DUMMYFUNCTION("""COMPUTED_VALUE"""),1.0) -> 1 | AT18: =IFERROR(__xludf.DUMMYFUNCTION("QUERY('Copy of John 1'!K1:M201, ""SELECT K, COUNT(M) WHERE K IS NOT NULL AND L = 'February' GROUP BY K ORDER BY COUNT(M) DESC LIMIT 5"", 1)"),"CustomerName") -> CustomerName | AU18: =IFERROR(__xludf.DUMMYFUNCTION("""COMPUTED_VALUE"""),"count OrderTotal") -> count OrderTotal
A19: SO00000172 | B19: 1200007688.00 | C19: ANTONIO'S GRILL | D19: 45299 | E19: 525.3 | F19: ANGELI SUMINGIT | K19: ANTONIO'S GRILL | L19: January | M19: 525.3 | AL19: =IFERROR(__xludf.DUMMYFUNCTION("""COMPUTED_VALUE"""),"ARM-G INT'L. LOGISTIC INC. Total") -> ARM-G INT'L. LOGISTIC INC. Total | AN19: =IFERROR(__xludf.DUMMYFUNCTION("""COMPUTED_VALUE"""),1.0) -> 1 | AP19: =IFERROR(__xludf.DUMMYFUNCTION("""COMPUTED_VALUE"""),"ARM-G INT'L. LOGISTIC INC. Total") -> ARM-G INT'L. LOGISTIC INC. Total | AR19: =IFERROR(__xludf.DUMMYFUNCTION("""COMPUTED_VALUE"""),1.0) -> 1 | AT19: =IFERROR(__xludf.DUMMYFUNCTION("""COMPUTED_VALUE"""),"MUNICIPALITY OF LUPON - LGU") -> MUNICIPALITY OF LUPON - LGU | AU19: =IFERROR(__xludf.DUMMYFUNCTION("""COMPUTED_VALUE"""),21.0) -> 21
A20: SO00000196 | B20: 1250000913.00 | C20: FAR EAST ASSOCIATES | D20: 45299 | E20: 2265.45 | F20: ANGELI SUMINGIT | K20: FAR EAST ASSOCIATES | L20: January | M20: 2265.45 | AL20: =IFERROR(__xludf.DUMMYFUNCTION("""COMPUTED_VALUE"""),"ASIAGLOBAL TECHNOLOGIES INC.") -> ASIAGLOBAL TECHNOLOGIES INC. | AM20: =IFERROR(__xludf.DUMMYFUNCTION("""COMPUTED_VALUE"""),"January") -> January | AN20: =IFERROR(__xludf.DUMMYFUNCTION("""COMPUTED_VALUE"""),1.0) -> 1 | AP20: =IFERROR(__xludf.DUMMYFUNCTION("""COMPUTED_VALUE"""),"ASIAGLOBAL TECHNOLOGIES INC.") -> ASIAGLOBAL TECHNOLOGIES INC. | AQ20: =IFERROR(__xludf.DUMMYFUNCTION("""COMPUTED_VALUE"""),"January") -> January | AR20: =IFERROR(__xludf.DUMMYFUNCTION("""COMPUTED_VALUE"""),1.0) -> 1 | AT20: =IFERROR(__xludf.DUMMYFUNCTION("""COMPUTED_VALUE"""),"STENIEL MINDANAO PACKAGING CORPORATION") -> STENIEL MINDANAO PACKAGING CORPORATION | AU20: =IFERROR(__xludf.DUMMYFUNCTION("""COMPUTED_VALUE"""),5.0) -> 5
A21: SO00000168 | B21: 1250010259.00 | C21: LAND BANK - TORIL BRANCH | D21: 45299 | E21: 3256 | F21: GRACE POLPOL | K21: LAND BANK - TORIL BRANCH | L21: January | M21: 3256 | AL21: =IFERROR(__xludf.DUMMYFUNCTION("""COMPUTED_VALUE"""),"ASIAGLOBAL TECHNOLOGIES INC. Total") -> ASIAGLOBAL TECHNOLOGIES INC. Total | AN21: =IFERROR(__xludf.DUMMYFUNCTION("""COMPUTED_VALUE"""),1.0) -> 1 | AP21: =IFERROR(__xludf.DUMMYFUNCTION("""COMPUTED_VALUE"""),"ASIAGLOBAL TECHNOLOGIES INC. Total") -> ASIAGLOBAL TECHNOLOGIES INC. Total | AR21: =IFERROR(__xludf.DUMMYFUNCTION("""COMPUTED_VALUE"""),1.0) -> 1 | AT21: =IFERROR(__xludf.DUMMYFUNCTION("""COMPUTED_VALUE"""),"EC GONZAGA ENTERPRISES") -> EC GONZAGA ENTERPRISES | AU21: =IFERROR(__xludf.DUMMYFUNCTION("""COMPUTED_VALUE"""),4.0) -> 4
A22: SO00000179 | B22: 1250009502.00 | C22: SIMC | D22: 45299 | E22: 4400.6 | F22: ANGELI SUMINGIT | K22: SIMC | L22: January | M22: 4400.6 | AL22: =IFERROR(__xludf.DUMMYFUNCTION("""COMPUTED_VALUE"""),"ASSUMPTION COLLEGE OF DAVAO INC") -> ASSUMPTION COLLEGE OF DAVAO INC | AM22: =IFERROR(__xludf.DUMMYFUNCTION("""COMPUTED_VALUE"""),"February") -> February | AN22: =IFERROR(__xludf.DUMMYFUNCTION("""COMPUTED_VALUE"""),2.0) -> 2 | AP22: =IFERROR(__xludf.DUMMYFUNCTION("""COMPUTED_VALUE"""),"ASSUMPTION COLLEGE OF DAVAO INC") -> ASSUMPTION COLLEGE OF DAVAO INC | AQ22: =IFERROR(__xludf.DUMMYFUNCTION("""COMPUTED_VALUE"""),"February") -> February | AR22: =IFERROR(__xludf.DUMMYFUNCTION("""COMPUTED_VALUE"""),2.0) -> 2 | AT22: =IFERROR(__xludf.DUMMYFUNCTION("""COMPUTED_VALUE"""),"AMALGATED CAPITAL INCORPORATED") -> AMALGATED CAPITAL INCORPORATED | AU22: =IFERROR(__xludf.DUMMYFUNCTION("""COMPUTED_VALUE"""),3.0) -> 3
A23: SO00000219 | B23: 1250010233.00 | C23: HELPMATE INCORPORATED | D23: 45299 | E23: 8254.15 | F23: ANGELI SUMINGIT | K23: HELPMATE INCORPORATED | L23: January | M23: 8254.15 | AL23: =IFERROR(__xludf.DUMMYFUNCTION("""COMPUTED_VALUE"""),"ASSUMPTION COLLEGE OF DAVAO INC Total") -> ASSUMPTION COLLEGE OF DAVAO INC Total | AN23: =IFERROR(__xludf.DUMMYFUNCTION("""COMPUTED_VALUE"""),2.0) -> 2 | AP23: =IFERROR(__xludf.DUMMYFUNCTION("""COMPUTED_VALUE"""),"ASSUMPTION COLLEGE OF DAVAO INC Total") -> ASSUMPTION COLLEGE OF DAVAO INC Total | AR23: =IFERROR(__xludf.DUMMYFUNCTION("""COMPUTED_VALUE"""),2.0) -> 2 | AT23: =IFERROR(__xludf.DUMMYFUNCTION("""COMPUTED_VALUE"""),"ASSUMPTION COLLEGE OF DAVAO INC") -> ASSUMPTION COLLEGE OF DAVAO INC | AU23: =IFERROR(__xludf.DUMMYFUNCTION("""COMPUTED_VALUE"""),2.0) -> 2
A24: SO00000190 | B24: 1250001764.00 | C24: STENIEL MINDANAO PACKAGING CORPORATION | D24: 45299 | E24: 111000 | F24: ANGELI SUMINGIT | K24: STENIEL MINDANAO PACKAGING CORPORATION | L24: January | M24: 111000 | AL24: =IFERROR(__xludf.DUMMYFUNCTION("""COMPUTED_VALUE"""),"ASTROBUILT CONSTRUCTION & DEVELOPMENT") -> ASTROBUILT CONSTRUCTION & DEVELOPMENT | AM24: =IFERROR(__xludf.DUMMYFUNCTION("""COMPUTED_VALUE"""),"January") -> January | AN24: =IFERROR(__xludf.DUMMYFUNCTION("""COMPUTED_VALUE"""),1.0) -> 1 | AP24: =IFERROR(__xludf.DUMMYFUNCTION("""COMPUTED_VALUE"""),"ASTROBUILT CONSTRUCTION & DEVELOPMENT") -> ASTROBUILT CONSTRUCTION & DEVELOPMENT | AQ24: =IFERROR(__xludf.DUMMYFUNCTION("""COMPUTED_VALUE"""),"January") -> January | AR24: =IFERROR(__xludf.DUMMYFUNCTION("""COMPUTED_VALUE"""),1.0) -> 1
A25: SO00000275 | B25: 1250001764.00 | C25: STENIEL MINDANAO PACKAGING CORPORATION | D25: 45300 | E25: 765 | F25: ANGELI SUMINGIT | K25: STENIEL MINDANAO PACKAGING CORPORATION | L25: January | M25: 765 | AL25: =IFERROR(__xludf.DUMMYFUNCTION("""COMPUTED_VALUE"""),"ASTROBUILT CONSTRUCTION & DEVELOPMENT Total") -> ASTROBUILT CONSTRUCTION & DEVELOPMENT Total | AN25: =IFERROR(__xludf.DUMMYFUNCTION("""COMPUTED_VALUE"""),1.0) -> 1 | AP25: =IFERROR(__xludf.DUMMYFUNCTION("""COMPUTED_VALUE"""),"ASTROBUILT CONSTRUCTION & DEVELOPMENT Total") -> ASTROBUILT CONSTRUCTION & DEVELOPMENT Total | AR25: =IFERROR(__xludf.DUMMYFUNCTION("""COMPUTED_VALUE"""),1.0) -> 1
A26: SO00000262 | B26: 1200007688.00 | C26: ANTONIO'S GRILL | D26: 45300 | E26: 1525 | F26: ANGELI SUMINGIT | K26: ANTONIO'S GRILL | L26: January | M26: 1525 | AL26: =IFERROR(__xludf.DUMMYFUNCTION("""COMPUTED_VALUE"""),"AUTOKID SOUTH MINDANAO CORP.") -> AUTOKID SOUTH MINDANAO CORP. | AM26: =IFERROR(__xludf.DUMMYFUNCTION("""COMPUTED_VALUE"""),"February") -> February | AN26: =IFERROR(__xludf.DUMMYFUNCTION("""COMPUTED_VALUE"""),1.0) -> 1 | AP26: =IFERROR(__xludf.DUMMYFUNCTION("""COMPUTED_VALUE"""),"AUTOKID SOUTH MINDANAO CORP.") -> AUTOKID SOUTH MINDANAO CORP. | AQ26: =IFERROR(__xludf.DUMMYFUNCTION("""COMPUTED_VALUE"""),"February") -> February | AR26: =IFERROR(__xludf.DUMMYFUNCTION("""COMPUTED_VALUE"""),1.0) -> 1 | AT26: =AVERAGEIF(AI2:AI1000, "January", AJ2:AJ1000) -> 1.4936709
A27: SO00000263 | B27: 1200007688.00 | C27: ANTONIO'S GRILL | D27: 45300 | E27: 1525 | F27: ANGELI SUMINGIT | K27: ANTONIO'S GRILL | L27: January | M27: 1525 | AL27: =IFERROR(__xludf.DUMMYFUNCTION("""COMPUTED_VALUE"""),"AUTOKID SOUTH MINDANAO CORP. Total") -> AUTOKID SOUTH MINDANAO CORP. Total | AN27: =IFERROR(__xludf.DUMMYFUNCTION("""COMPUTED_VALUE"""),1.0) -> 1 | AP27: =IFERROR(__xludf.DUMMYFUNCTION("""COMPUTED_VALUE"""),"AUTOKID SOUTH MINDANAO CORP. Total") -> AUTOKID SOUTH MINDANAO CORP. Total | AR27: =IFERROR(__xludf.DUMMYFUNCTION("""COMPUTED_VALUE"""),1.0) -> 1 | AT27: =AVERAGEIF(AI2:AI1000, "February", AJ2:AJ1000) -> 1.7608696
A28: SO00000265 | B28: 1200007688.00 | C28: ANTONIO'S GRILL | D28: 45300 | E28: 1525 | F28: ANGELI SUMINGIT | K28: ANTONIO'S GRILL | L28: January | M28: 1525 | AL28: =IFERROR(__xludf.DUMMYFUNCTION("""COMPUTED_VALUE"""),"B.P.I. - HOUSING LOAN") -> B.P.I. - HOUSING LOAN | AM28: =IFERROR(__xludf.DUMMYFUNCTION("""COMPUTED_VALUE"""),"January") -> January | AN28: =IFERROR(__xludf.DUMMYFUNCTION("""COMPUTED_VALUE"""),1.0) -> 1 | AP28: =IFERROR(__xludf.DUMMYFUNCTION("""COMPUTED_VALUE"""),"B.P.I. - HOUSING LOAN") -> B.P.I. - HOUSING LOAN | AQ28: =IFERROR(__xludf.DUMMYFUNCTION("""COMPUTED_VALUE"""),"January") -> January | AR28: =IFERROR(__xludf.DUMMYFUNCTION("""COMPUTED_VALUE"""),1.0) -> 1
A29: SO00000266 | B29: 1200007688.00 | C29: ANTONIO'S GRILL | D29: 45300 | E29: 1525 | F29: ANGELI SUMINGIT | K29: ANTONIO'S GRILL | L29: January | M29: 1525 | AL29: =IFERROR(__xludf.DUMMYFUNCTION("""COMPUTED_VALUE"""),"B.P.I. - HOUSING LOAN Total") -> B.P.I. - HOUSING LOAN Total | AN29: =IFERROR(__xludf.DUMMYFUNCTION("""COMPUTED_VALUE"""),1.0) -> 1 | AP29: =IFERROR(__xludf.DUMMYFUNCTION("""COMPUTED_VALUE"""),"B.P.I. - HOUSING LOAN Total") -> B.P.I. - HOUSING LOAN Total | AR29: =IFERROR(__xludf.DUMMYFUNCTION("""COMPUTED_VALUE"""),1.0) -> 1
A30: SO00000245 | B30: 1250002203.00 | C30: EHB ENTERPRISES & PRINTHAUS | D30: 45300 | E30: 2050 | F30: ANGELI SUMINGIT | K30: EHB ENTERPRISES & PRINTHAUS | L30: January | M30: 2050 | AL30: =IFERROR(__xludf.DUMMYFUNCTION("""COMPUTED_VALUE"""),"B.P.I. - BAJADA (FRONTING CONPINCO)") -> B.P.I. - BAJADA (FRONTING CONPINCO) | AM30: =IFERROR(__xludf.DUMMYFUNCTION("""COMPUTED_VALUE"""),"January") -> January | AN30: =IFERROR(__xludf.DUMMYFUNCTION("""COMPUTED_VALUE"""),1.0) -> 1 | AP30: =IFERROR(__xludf.DUMMYFUNCTION("""COMPUTED_VALUE"""),"B.P.I. - BAJADA (FRONTING CONPINCO)") -> B.P.I. - BAJADA (FRONTING CONPINCO) | AQ30: =IFERROR(__xludf.DUMMYFUNCTION("""COMPUTED_VALUE"""),"January") -> January | AR30: =IFERROR(__xludf.DUMMYFUNCTION("""COMPUTED_VALUE"""),1.0) -> 1
A31: SO00000247 | B31: 1250009745.00 | C31: ML PREMIUM RESOURCES CORP. | D31: 45300 | E31: 3571.75 | F31: ANGELI SUMINGIT | K31: ML PREMIUM RESOURCES CORP. | L31: January | M31: 3571.75 | AL31: =IFERROR(__xludf.DUMMYFUNCTION("""COMPUTED_VALUE"""),"B.P.I. - BAJADA (FRONTING CONPINCO) Total") -> B.P.I. - BAJADA (FRONTING CONPINCO) Total | AN31: =IFERROR(__xludf.DUMMYFUNCTION("""COMPUTED_VALUE"""),1.0) -> 1 | AP31: =IFERROR(__xludf.DUMMYFUNCTION("""COMPUTED_VALUE"""),"B.P.I. - BAJADA (FRONTING CONPINCO) Total") -> B.P.I. - BAJADA (FRONTING CONPINCO) Total | AR31: =IFERROR(__xludf.DUMMYFUNCTION("""COMPUTED_VALUE"""),1.0) -> 1
A32: SO00000296 | B32: 1200008920.00 | C32: ARM-G INT'L. LOGISTIC INC. | D32: 45301 | E32: 5151 | F32: ANGELI SUMINGIT | K32: ARM-G INT'L. LOGISTIC INC. | L32: January | M32: 5151 | AL32: =IFERROR(__xludf.DUMMYFUNCTION("""COMPUTED_VALUE"""),"B.P.I. - LANANG") -> B.P.I. - LANANG | AM32: =IFERROR(__xludf.DUMMYFUNCTION("""COMPUTED_VALUE"""),"January") -> January | AN32: =IFERROR(__xludf.DUMMYFUNCTION("""COMPUTED_VALUE"""),1.0) -> 1 | AP32: =IFERROR(__xludf.DUMMYFUNCTION("""COMPUTED_VALUE"""),"B.P.I. - LANANG") -> B.P.I. - LANANG | AQ32: =IFERROR(__xludf.DUMMYFUNCTION("""COMPUTED_VALUE"""),"January") -> January | AR32: =IFERROR(__xludf.DUMMYFUNCTION("""COMPUTED_VALUE"""),1.0) -> 1
A33: SO00000313 | B33: 1200007890.00 | C33: ASTROBUILT CONSTRUCTION & DEVELOPMENT | D33: 45301 | E33: 7885.3 | F33: ANGELI SUMINGIT | K33: ASTROBUILT CONSTRUCTION & DEVELOPMENT | L33: January | M33: 7885.3 | AL33: =IFERROR(__xludf.DUMMYFUNCTION("""COMPUTED_VALUE"""),"B.P.I. - LANANG Total") -> B.P.I. - LANANG Total | AN33: =IFERROR(__xludf.DUMMYFUNCTION("""COMPUTED_VALUE"""),1.0) -> 1 | AP33: =IFERROR(__xludf.DUMMYFUNCTION("""COMPUTED_VALUE"""),"B.P.I. - LANANG Total") -> B.P.I. - LANANG Total | AR33: =IFERROR(__xludf.DUMMYFUNCTION("""COMPUTED_VALUE"""),1.0) -> 1
A34: SO00000337 | B34: 1250009892.00 | C34: EC GONZAGA ENTERPRISES | D34: 45301 | E34: 10250.5 | F34: ANGELI SUMINGIT | K34: EC GONZAGA ENTERPRISES | L34: January | M34: 10250.5 | AL34: =IFERROR(__xludf.DUMMYFUNCTION("""COMPUTED_VALUE"""),"BANEXCO TRADERS INC.") -> BANEXCO TRADERS INC. | AM34: =IFERROR(__xludf.DUMMYFUNCTION("""COMPUTED_VALUE"""),"January") -> January | AN34: =IFERROR(__xludf.DUMMYFUNCTION("""COMPUTED_VALUE"""),1.0) -> 1 | AP34: =IFERROR(__xludf.DUMMYFUNCTION("""COMPUTED_VALUE"""),"BANEXCO TRADERS INC.") -> BANEXCO TRADERS INC. | AQ34: =IFERROR(__xludf.DUMMYFUNCTION("""COMPUTED_VALUE"""),"January") -> January | AR34: =IFERROR(__xludf.DUMMYFUNCTION("""COMPUTED_VALUE"""),1.0) -> 1
A35: SO00000334 | B35: 1250009892.00 | C35: EC GONZAGA ENTERPRISES | D35: 45301 | E35: 16973.25 | F35: ANGELI SUMINGIT | K35: EC GONZAGA ENTERPRISES | L35: January | M35: 16973.25 | AL35: =IFERROR(__xludf.DUMMYFUNCTION("""COMPUTED_VALUE"""),"BANEXCO TRADERS INC. Total") -> BANEXCO TRADERS INC. Total | AN35: =IFERROR(__xludf.DUMMYFUNCTION("""COMPUTED_VALUE"""),1.0) -> 1 | AP35: =IFERROR(__xludf.DUMMYFUNCTION("""COMPUTED_VALUE"""),"BANEXCO TRADERS INC. Total") -> BANEXCO TRADERS INC. Total | AR35: =IFERROR(__xludf.DUMMYFUNCTION("""COMPUTED_VALUE"""),1.0) -> 1
A36: SO00000357 | B36: 1250010341.00 | C36: EQUINOX SYNERGY OPC | D36: 45302 | E36: 1154 | F36: ANGELI SUMINGIT | K36: EQUINOX SYNERGY OPC | L36: January | M36: 1154 | AL36: =IFERROR(__xludf.DUMMYFUNCTION("""COMPUTED_VALUE"""),"CHARVERSON WOOD INDUSTRY INC.") -> CHARVERSON WOOD INDUSTRY INC. | AM36: =IFERROR(__xludf.DUMMYFUNCTION("""COMPUTED_VALUE"""),"January") -> January | AN36: =IFERROR(__xludf.DUMMYFUNCTION("""COMPUTED_VALUE"""),2.0) -> 2 | AP36: =IFERROR(__xludf.DUMMYFUNCTION("""COMPUTED_VALUE"""),"CHARVERSON WOOD INDUSTRY INC.") -> CHARVERSON WOOD INDUSTRY INC. | AQ36: =IFERROR(__xludf.DUMMYFUNCTION("""COMPUTED_VALUE"""),"January") -> January | AR36: =IFERROR(__xludf.DUMMYFUNCTION("""COMPUTED_VALUE"""),2.0) -> 2
A37: SO00000364 | B37: 1250010341.00 | C37: EQUINOX SYNERGY OPC | D37: 45302 | E37: 3031.5 | F37: ANGELI SUMINGIT | K37: EQUINOX SYNERGY OPC | L37: January | M37: 3031.5 | AL37: =IFERROR(__xludf.DUMMYFUNCTION("""COMPUTED_VALUE"""),"CHARVERSON WOOD INDUSTRY INC. Total") -> CHARVERSON WOOD INDUSTRY INC. Total | AN37: =IFERROR(__xludf.DUMMYFUNCTION("""COMPUTED_VALUE"""),2.0) -> 2 | AP37: =IFERROR(__xludf.DUMMYFUNCTION("""COMPUTED_VALUE"""),"CHARVERSON WOOD INDUSTRY INC. Total") -> CHARVERSON WOOD INDUSTRY INC. Total | AR37: =IFERROR(__xludf.DUMMYFUNCTION("""COMPUTED_VALUE"""),2.0) -> 2
A38: SO00000342 | B38: 1250001348.00 | C38: BANEXCO TRADERS INC. | D38: 45302 | E38: 4490.4 | F38: ANGELI SUMINGIT | K38: BANEXCO TRADERS INC. | L38: January | M38: 4490.4 | AL38: =IFERROR(__xludf.DUMMYFUNCTION("""COMPUTED_VALUE"""),"CHEVRON PHILIPPINES INC. (FORMER CALTEX)") -> CHEVRON PHILIPPINES INC. (FORMER CALTEX) | AM38: =IFERROR(__xludf.DUMMYFUNCTION("""COMPUTED_VALUE"""),"February") -> February | AN38: =IFERROR(__xludf.DUMMYFUNCTION("""COMPUTED_VALUE"""),1.0) -> 1 | AP38: =IFERROR(__xludf.DUMMYFUNCTION("""COMPUTED_VALUE"""),"CHEVRON PHILIPPINES INC. (FORMER CALTEX)") -> CHEVRON PHILIPPINES INC. (FORMER CALTEX) | AQ38: =IFERROR(__xludf.DUMMYFUNCTION("""COMPUTED_VALUE"""),"February") -> February | AR38: =IFERROR(__xludf.DUMMYFUNCTION("""COMPUTED_VALUE"""),1.0) -> 1
A39: SO00000346 | B39: 1250000034.00 | C39: LAND BANK OF THE PHILS. - RAMON MAGSAYSAY | D39: 45302 | E39: 10550 | F39: GRACE POLPOL | K39: LAND BANK OF THE PHILS. - RAMON MAGSAYSAY | L39: January | M39: 10550 | AL39: =IFERROR(__xludf.DUMMYFUNCTION("""COMPUTED_VALUE"""),"CHEVRON PHILIPPINES INC. (FORMER CALTEX) Total") -> CHEVRON PHILIPPINES INC. (FORMER CALTEX) Total | AN39: =IFERROR(__xludf.DUMMYFUNCTION("""COMPUTED_VALUE"""),1.0) -> 1 | AP39: =IFERROR(__xludf.DUMMYFUNCTION("""COMPUTED_VALUE"""),"CHEVRON PHILIPPINES INC. (FORMER CALTEX) Total") -> CHEVRON PHILIPPINES INC. (FORMER CALTEX) Total | AR39: =IFERROR(__xludf.DUMMYFUNCTION("""COMPUTED_VALUE"""),1.0) -> 1
A40: SO00000402 | B40: 1250009745.00 | C40: ML PREMIUM RESOURCES CORP. | D40: 45303 | E40: 744 | F40: ANGELI SUMINGIT | K40: ML PREMIUM RESOURCES CORP. | L40: January | M40: 744 | AL40: =IFERROR(__xludf.DUMMYFUNCTION("""COMPUTED_VALUE"""),"CITY GOVERNMENT OF DAVAO") -> CITY GOVERNMENT OF DAVAO | AM40: =IFERROR(__xludf.DUMMYFUNCTION("""COMPUTED_VALUE"""),"November") -> November | AN40: =IFERROR(__xludf.DUMMYFUNCTION("""COMPUTED_VALUE"""),1.0) -> 1 | AP40: =IFERROR(__xludf.DUMMYFUNCTION("""COMPUTED_VALUE"""),"CITY GOVERNMENT OF DAVAO") -> CITY GOVERNMENT OF DAVAO | AQ40: =IFERROR(__xludf.DUMMYFUNCTION("""COMPUTED_VALUE"""),"November") -> November | AR40: =IFERROR(__xludf.DUMMYFUNCTION("""COMPUTED_VALUE"""),1.0) -> 1
A41: SO00000399 | B41: 1250004887.00 | C41: EZGAB CORPORATION | D41: 45303 | E41: 1873.1 | F41: ANGELI SUMINGIT | K41: EZGAB CORPORATION | L41: January | M41: 1873.1 | AL41: =IFERROR(__xludf.DUMMYFUNCTION("""COMPUTED_VALUE"""),"CITY GOVERNMENT OF DAVAO Total") -> CITY GOVERNMENT OF DAVAO Total | AN41: =IFERROR(__xludf.DUMMYFUNCTION("""COMPUTED_VALUE"""),1.0) -> 1 | AP41: =IFERROR(__xludf.DUMMYFUNCTION("""COMPUTED_VALUE"""),"CITY GOVERNMENT OF DAVAO Total") -> CITY GOVERNMENT OF DAVAO Total | AR41: =IFERROR(__xludf.DUMMYFUNCTION("""COMPUTED_VALUE"""),1.0) -> 1
A42: SO00000403 | B42: 1250009745.00 | C42: ML PREMIUM RESOURCES CORP. | D42: 45303 | E42: 1995.5 | F42: ANGELI SUMINGIT | K42: ML PREMIUM RESOURCES CORP. | L42: January | M42: 1995.5 | AL42: =IFERROR(__xludf.DUMMYFUNCTION("""COMPUTED_VALUE"""),"CIVIL SERVICE COMMISSION-REG. XI") -> CIVIL SERVICE COMMISSION-REG. XI | AM42: =IFERROR(__xludf.DUMMYFUNCTION("""COMPUTED_VALUE"""),"February") -> February | AN42: =IFERROR(__xludf.DUMMYFUNCTION("""COMPUTED_VALUE"""),1.0) -> 1 | AP42: =IFERROR(__xludf.DUMMYFUNCTION("""COMPUTED_VALUE"""),"CIVIL SERVICE COMMISSION-REG. XI") -> CIVIL SERVICE COMMISSION-REG. XI | AQ42: =IFERROR(__xludf.DUMMYFUNCTION("""COMPUTED_VALUE"""),"February") -> February | AR42: =IFERROR(__xludf.DUMMYFUNCTION("""COMPUTED_VALUE"""),1.0) -> 1
A43: SO00000405 | B43: 1250003753.00 | C43: FOCUSINC GROUP CORP. | D43: 45303 | E43: 2113.6 | F43: ANGELI SUMINGIT | K43: FOCUSINC GROUP CORP. | L43: January | M43: 2113.6 | AM43: =IFERROR(__xludf.DUMMYFUNCTION("""COMPUTED_VALUE"""),"January") -> January | AN43: =IFERROR(__xludf.DUMMYFUNCTION("""COMPUTED_VALUE"""),5.0) -> 5 | AQ43: =IFERROR(__xludf.DUMMYFUNCTION("""COMPUTED_VALUE"""),"January") -> January | AR43: =IFERROR(__xludf.DUMMYFUNCTION("""COMPUTED_VALUE"""),5.0) -> 5
A44: SO00000398 | B44: 1250000438.00 | C44: CIVIL SERVICE COMMISSION-REG. XI | D44: 45303 | E44: 4800 | F44: GRACE POLPOL | K44: CIVIL SERVICE COMMISSION-REG. XI | L44: January | M44: 4800 | AL44: =IFERROR(__xludf.DUMMYFUNCTION("""COMPUTED_VALUE"""),"CIVIL SERVICE COMMISSION-REG. XI Total") -> CIVIL SERVICE COMMISSION-REG. XI Total | AN44: =IFERROR(__xludf.DUMMYFUNCTION("""COMPUTED_VALUE"""),6.0) -> 6 | AP44: =IFERROR(__xludf.DUMMYFUNCTION("""COMPUTED_VALUE"""),"CIVIL SERVICE COMMISSION-REG. XI Total") -> CIVIL SERVICE COMMISSION-REG. XI Total | AR44: =IFERROR(__xludf.DUMMYFUNCTION("""COMPUTED_VALUE"""),6.0) -> 6
A45: SO00000436 | B45: 1250001496.00 | C45: COMFAC CORPORATION | D45: 45304 | E45: 711 | F45: ANGELI SUMINGIT | K45: COMFAC CORPORATION | L45: January | M45: 711 | AL45: =IFERROR(__xludf.DUMMYFUNCTION("""COMPUTED_VALUE"""),"COMFAC CORPORATION") -> COMFAC CORPORATION | AM45: =IFERROR(__xludf.DUMMYFUNCTION("""COMPUTED_VALUE"""),"January") -> January | AN45: =IFERROR(__xludf.DUMMYFUNCTION("""COMPUTED_VALUE"""),4.0) -> 4 | AP45: =IFERROR(__xludf.DUMMYFUNCTION("""COMPUTED_VALUE"""),"COMFAC CORPORATION") -> COMFAC CORPORATION | AQ45: =IFERROR(__xludf.DUMMYFUNCTION("""COMPUTED_VALUE"""),"January") -> January | AR45: =IFERROR(__xludf.DUMMYFUNCTION("""COMPUTED_VALUE"""),4.0) -> 4
A46: SO00000434 | B46: 1250001496.00 | C46: COMFAC CORPORATION | D46: 45304 | E46: 1289.35 | F46: ANGELI SUMINGIT | K46: COMFAC CORPORATION | L46: January | M46: 1289.35 | AL46: =IFERROR(__xludf.DUMMYFUNCTION("""COMPUTED_VALUE"""),"COMFAC CORPORATION Total") -> COMFAC CORPORATION Total | AN46: =IFERROR(__xludf.DUMMYFUNCTION("""COMPUTED_VALUE"""),4.0) -> 4 | AP46: =IFERROR(__xludf.DUMMYFUNCTION("""COMPUTED_VALUE"""),"COMFAC CORPORATION Total") -> COMFAC CORPORATION Total | AR46: =IFERROR(__xludf.DUMMYFUNCTION("""COMPUTED_VALUE"""),4.0) -> 4
A47: SO00000437 | B47: 1250001496.00 | C47: COMFAC CORPORATION | D47: 45304 | E47: 1806 | F47: ANGELI SUMINGIT | K47: COMFAC CORPORATION | L47: January | M47: 1806 | AL47: =IFERROR(__xludf.DUMMYFUNCTION("""COMPUTED_VALUE"""),"COMMISSION ON AUDIT") -> COMMISSION ON AUDIT | AM47: =IFERROR(__xludf.DUMMYFUNCTION("""COMPUTED_VALUE"""),"February") -> February | AN47: =IFERROR(__xludf.DUMMYFUNCTION("""COMPUTED_VALUE"""),1.0) -> 1 | AP47: =IFERROR(__xludf.DUMMYFUNCTION("""COMPUTED_VALUE"""),"COMMISSION ON AUDIT") -> COMMISSION ON AUDIT | AQ47: =IFERROR(__xludf.DUMMYFUNCTION("""COMPUTED_VALUE"""),"February") -> February | AR47: =IFERROR(__xludf.DUMMYFUNCTION("""COMPUTED_VALUE"""),1.0) -> 1
A48: SO00000243 | B48: 1200007409.00 | C48: NAKASHIN DAVAO INTERNATIONAL INC. | D48: 45306 | E48: 3700.8 | F48: ANGELI SUMINGIT | K48: NAKASHIN DAVAO INTERNATIONAL INC. | L48: January | M48: 3700.8 | AL48: =IFERROR(__xludf.DUMMYFUNCTION("""COMPUTED_VALUE"""),"COMMISSION ON AUDIT Total") -> COMMISSION ON AUDIT Total | AN48: =IFERROR(__xludf.DUMMYFUNCTION("""COMPUTED_VALUE"""),1.0) -> 1 | AP48: =IFERROR(__xludf.DUMMYFUNCTION("""COMPUTED_VALUE"""),"COMMISSION ON AUDIT Total") -> COMMISSION ON AUDIT Total | AR48: =IFERROR(__xludf.DUMMYFUNCTION("""COMPUTED_VALUE"""),1.0) -> 1
A49: SO00000464 | B49: 1250004371.00 | C49: PNJK INC | D49: 45306 | E49: 3720 | F49: ANGELI SUMINGIT | K49: PNJK INC | L49: January | M49: 3720 | AL49: =IFERROR(__xludf.DUMMYFUNCTION("""COMPUTED_VALUE"""),"CONSULATE GENERAL OF JAPAN") -> CONSULATE GENERAL OF JAPAN | AM49: =IFERROR(__xludf.DUMMYFUNCTION("""COMPUTED_VALUE"""),"February") -> February | AN49: =IFERROR(__xludf.DUMMYFUNCTION("""COMPUTED_VALUE"""),2.0) -> 2 | AP49: =IFERROR(__xludf.DUMMYFUNCTION("""COMPUTED_VALUE"""),"CONSULATE GENERAL OF JAPAN") -> CONSULATE GENERAL OF JAPAN | AQ49: =IFERROR(__xludf.DUMMYFUNCTION("""COMPUTED_VALUE"""),"February") -> February | AR49: =IFERROR(__xludf.DUMMYFUNCTION("""COMPUTED_VALUE"""),2.0) -> 2
A50: SO00000463 | B50: 1200008426.00 | C50: B.P.I. - HOUSING LOAN | D50: 45306 | E50: 5500 | F50: ANGELI SUMINGIT | K50: B.P.I. - HOUSING LOAN | L50: January | M50: 5500 | AL50: =IFERROR(__xludf.DUMMYFUNCTION("""COMPUTED_VALUE"""),"CONSULATE GENERAL OF JAPAN Total") -> CONSULATE GENERAL OF JAPAN Total | AN50: =IFERROR(__xludf.DUMMYFUNCTION("""COMPUTED_VALUE"""),2.0) -> 2 | AP50: =IFERROR(__xludf.DUMMYFUNCTION("""COMPUTED_VALUE"""),"CONSULATE GENERAL OF JAPAN Total") -> CONSULATE GENERAL OF JAPAN Total | AR50: =IFERROR(__xludf.DUMMYFUNCTION("""COMPUTED_VALUE"""),2.0) -> 2
A51: SO00000488 | B51: 1250010348.00 | C51: LICSAL CONSTRUCTION CORP. | D51: 45306 | E51: 15998 | F51: Vivian Chavez | K51: LICSAL CONSTRUCTION CORP. | L51: January | M51: 15998 | AL51: =IFERROR(__xludf.DUMMYFUNCTION("""COMPUTED_VALUE"""),"DAVAO CONCRETE POLES CORPORATION") -> DAVAO CONCRETE POLES CORPORATION | AM51: =IFERROR(__xludf.DUMMYFUNCTION("""COMPUTED_VALUE"""),"February") -> February | AN51: =IFERROR(__xludf.DUMMYFUNCTION("""COMPUTED_VALUE"""),2.0) -> 2 | AP51: =IFERROR(__xludf.DUMMYFUNCTION("""COMPUTED_VALUE"""),"DAVAO CONCRETE POLES CORPORATION") -> DAVAO CONCRETE POLES CORPORATION | AQ51: =IFERROR(__xludf.DUMMYFUNCTION("""COMPUTED_VALUE"""),"February") -> February | AR51: =IFERROR(__xludf.DUMMYFUNCTION("""COMPUTED_VALUE"""),2.0) -> 2
A52: SO00000498 | B52: 1250001764.00 | C52: STENIEL MINDANAO PACKAGING CORPORATION | D52: 45307 | E52: 324 | F52: ANGELI SUMINGIT | K52: STENIEL MINDANAO PACKAGING CORPORATION | L52: January | M52: 324 | AM52: =IFERROR(__xludf.DUMMYFUNCTION("""COMPUTED_VALUE"""),"January") -> January | AN52: =IFERROR(__xludf.DUMMYFUNCTION("""COMPUTED_VALUE"""),1.0) -> 1 | AQ52: =IFERROR(__xludf.DUMMYFUNCTION("""COMPUTED_VALUE"""),"January") -> January | AR52: =IFERROR(__xludf.DUMMYFUNCTION("""COMPUTED_VALUE"""),1.0) -> 1
A53: SO00000510 | B53: 1250004887.00 | C53: EZGAB CORPORATION | D53: 45307 | E53: 569.8 | F53: ANGELI SUMINGIT | K53: EZGAB CORPORATION | L53: January | M53: 569.8 | AL53: =IFERROR(__xludf.DUMMYFUNCTION("""COMPUTED_VALUE"""),"DAVAO CONCRETE POLES CORPORATION Total") -> DAVAO CONCRETE POLES CORPORATION Total | AN53: =IFERROR(__xludf.DUMMYFUNCTION("""COMPUTED_VALUE"""),3.0) -> 3 | AP53: =IFERROR(__xludf.DUMMYFUNCTION("""COMPUTED_VALUE"""),"DAVAO CONCRETE POLES CORPORATION Total") -> DAVAO CONCRETE POLES CORPORATION Total | AR53: =IFERROR(__xludf.DUMMYFUNCTION("""COMPUTED_VALUE"""),3.0) -> 3
A54: SO00000518 | B54: 1250001319.00 | C54: REJOICE FAMILY FOODS | D54: 45307 | E54: 1172 | F54: ANGELI SUMINGIT | K54: REJOICE FAMILY FOODS | L54: January | M54: 1172 | AL54: =IFERROR(__xludf.DUMMYFUNCTION("""COMPUTED_VALUE"""),"DAVAO EYEMDS LASER AND SURGERY CENTER") -> DAVAO EYEMDS LASER AND SURGERY CENTER | AM54: =IFERROR(__xludf.DUMMYFUNCTION("""COMPUTED_VALUE"""),"February") -> February | AN54: =IFERROR(__xludf.DUMMYFUNCTION("""COMPUTED_VALUE"""),1.0) -> 1 | AP54: =IFERROR(__xludf.DUMMYFUNCTION("""COMPUTED_VALUE"""),"DAVAO EYEMDS LASER AND SURGERY CENTER") -> DAVAO EYEMDS LASER AND SURGERY CENTER | AQ54: =IFERROR(__xludf.DUMMYFUNCTION("""COMPUTED_VALUE"""),"February") -> February | AR54: =IFERROR(__xludf.DUMMYFUNCTION("""COMPUTED_VALUE"""),1.0) -> 1
A55: SO00000501 | B55: 1250002059.00 | C55: AGRI DAVAO INCORPORATED | D55: 45307 | E55: 2526.5 | F55: ANGELI SUMINGIT | K55: AGRI DAVAO INCORPORATED | L55: January | M55: 2526.5 | AL55: =IFERROR(__xludf.DUMMYFUNCTION("""COMPUTED_VALUE"""),"DAVAO EYEMDS LASER AND SURGERY CENTER Total") -> DAVAO EYEMDS LASER AND SURGERY CENTER Total | AN55: =IFERROR(__xludf.DUMMYFUNCTION("""COMPUTED_VALUE"""),1.0) -> 1 | AP55: =IFERROR(__xludf.DUMMYFUNCTION("""COMPUTED_VALUE"""),"DAVAO EYEMDS LASER AND SURGERY CENTER Total") -> DAVAO EYEMDS LASER AND SURGERY CENTER Total | AR55: =IFERROR(__xludf.DUMMYFUNCTION("""COMPUTED_VALUE"""),1.0) -> 1
A56: SO00000514 | B56: 1250001319.00 | C56: REJOICE FAMILY FOODS | D56: 45307 | E56: 2759.8 | F56: ANGELI SUMINGIT | K56: REJOICE FAMILY FOODS | L56: January | M56: 2759.8 | AL56: =IFERROR(__xludf.DUMMYFUNCTION("""COMPUTED_VALUE"""),"DAVAO FIBREBOARD PACKAGING PLANT INC.") -> DAVAO FIBREBOARD PACKAGING PLANT INC. | AM56: =IFERROR(__xludf.DUMMYFUNCTION("""COMPUTED_VALUE"""),"January") -> January | AN56: =IFERROR(__xludf.DUMMYFUNCTION("""COMPUTED_VALUE"""),1.0) -> 1 | AP56: =IFERROR(__xludf.DUMMYFUNCTION("""COMPUTED_VALUE"""),"DAVAO FIBREBOARD PACKAGING PLANT INC.") -> DAVAO FIBREBOARD PACKAGING PLANT INC. | AQ56: =IFERROR(__xludf.DUMMYFUNCTION("""COMPUTED_VALUE"""),"January") -> January | AR56: =IFERROR(__xludf.DUMMYFUNCTION("""COMPUTED_VALUE"""),1.0) -> 1
A57: SO00000515 | B57: 1250001319.00 | C57: REJOICE FAMILY FOODS | D57: 45307 | E57: 3290 | F57: ANGELI SUMINGIT | K57: REJOICE FAMILY FOODS | L57: January | M57: 3290 | AL57: =IFERROR(__xludf.DUMMYFUNCTION("""COMPUTED_VALUE"""),"DAVAO FIBREBOARD PACKAGING PLANT INC. Total") -> DAVAO FIBREBOARD PACKAGING PLANT INC. Total | AN57: =IFERROR(__xludf.DUMMYFUNCTION("""COMPUTED_VALUE"""),1.0) -> 1 | AP57: =IFERROR(__xludf.DUMMYFUNCTION("""COMPUTED_VALUE"""),"DAVAO FIBREBOARD PACKAGING PLANT INC. Total") -> DAVAO FIBREBOARD PACKAGING PLANT INC. Total | AR57: =IFERROR(__xludf.DUMMYFUNCTION("""COMPUTED_VALUE"""),1.0) -> 1
A58: SO00000527 | B58: 1250003015.00 | C58: CHARVERSON WOOD INDUSTRY INC. | D58: 45307 | E58: 3818.7 | F58: ANGELI SUMINGIT | K58: CHARVERSON WOOD INDUSTRY INC. | L58: January | M58: 3818.7 | AL58: =IFERROR(__xludf.DUMMYFUNCTION("""COMPUTED_VALUE"""),"DAVAO GENERAL HARDWARE COMPANY") -> DAVAO GENERAL HARDWARE COMPANY | AM58: =IFERROR(__xludf.DUMMYFUNCTION("""COMPUTED_VALUE"""),"February") -> February | AN58: =IFERROR(__xludf.DUMMYFUNCTION("""COMPUTED_VALUE"""),1.0) -> 1 | AP58: =IFERROR(__xludf.DUMMYFUNCTION("""COMPUTED_VALUE"""),"DAVAO GENERAL HARDWARE COMPANY") -> DAVAO GENERAL HARDWARE COMPANY | AQ58: =IFERROR(__xludf.DUMMYFUNCTION("""COMPUTED_VALUE"""),"February") -> February | AR58: =IFERROR(__xludf.DUMMYFUNCTION("""COMPUTED_VALUE"""),1.0) -> 1
A59: SO00000500 | B59: 1250003015.00 | C59: CHARVERSON WOOD INDUSTRY INC. | D59: 45307 | E59: 4312 | F59: ANGELI SUMINGIT | K59: CHARVERSON WOOD INDUSTRY INC. | L59: January | M59: 4312 | AL59: =IFERROR(__xludf.DUMMYFUNCTION("""COMPUTED_VALUE"""),"DAVAO GENERAL HARDWARE COMPANY Total") -> DAVAO GENERAL HARDWARE COMPANY Total | AN59: =IFERROR(__xludf.DUMMYFUNCTION("""COMPUTED_VALUE"""),1.0) -> 1 | AP59: =IFERROR(__xludf.DUMMYFUNCTION("""COMPUTED_VALUE"""),"DAVAO GENERAL HARDWARE COMPANY Total") -> DAVAO GENERAL HARDWARE COMPANY Total | AR59: =IFERROR(__xludf.DUMMYFUNCTION("""COMPUTED_VALUE"""),1.0) -> 1
A60: SO00000535 | B60: 1250001780.00 | C60: DAVAO CONCRETE POLES CORPORATION | D60: 45308 | E60: 773 | F60: ANGELI SUMINGIT | K60: DAVAO CONCRETE POLES CORPORATION | L60: January | M60: 773 | AL60: =IFERROR(__xludf.DUMMYFUNCTION("""COMPUTED_VALUE"""),"DEPARTMENT OF BUDGET & MANAGEMENT") -> DEPARTMENT OF BUDGET & MANAGEMENT | AM60: =IFERROR(__xludf.DUMMYFUNCTION("""COMPUTED_VALUE"""),"February") -> February | AN60: =IFERROR(__xludf.DUMMYFUNCTION("""COMPUTED_VALUE"""),1.0) -> 1 | AP60: =IFERROR(__xludf.DUMMYFUNCTION("""COMPUTED_VALUE"""),"DEPARTMENT OF BUDGET & MANAGEMENT") -> DEPARTMENT OF BUDGET & MANAGEMENT | AQ60: =IFERROR(__xludf.DUMMYFUNCTION("""COMPUTED_VALUE"""),"February") -> February | AR60: =IFERROR(__xludf.DUMMYFUNCTION("""COMPUTED_VALUE"""),1.0) -> 1
A61: SO00000538 | B61: 1200008537.00 | C61: KALINGAP PHARMACY | D61: 45308 | E61: 2586 | F61: ANGELI SUMINGIT | K61: KALINGAP PHARMACY | L61: January | M61: 2586 | AL61: =IFERROR(__xludf.DUMMYFUNCTION("""COMPUTED_VALUE"""),"DEPARTMENT OF BUDGET & MANAGEMENT Total") -> DEPARTMENT OF BUDGET & MANAGEMENT Total | AN61: =IFERROR(__xludf.DUMMYFUNCTION("""COMPUTED_VALUE"""),1.0) -> 1 | AP61: =IFERROR(__xludf.DUMMYFUNCTION("""COMPUTED_VALUE"""),"DEPARTMENT OF BUDGET & MANAGEMENT Total") -> DEPARTMENT OF BUDGET & MANAGEMENT Total | AR61: =IFERROR(__xludf.DUMMYFUNCTION("""COMPUTED_VALUE"""),1.0) -> 1
A62: SO00000540 | B62: 1250009423.00 | C62: SILANGAN MULTI-PURPOSE COOPERATIVE - BUHANGIN | D62: 45308 | E62: 3382.85 | F62: ANGELI SUMINGIT | K62: SILANGAN MULTI-PURPOSE COOPERATIVE - BUHANGIN | L62: January | M62: 3382.85 | AL62: =IFERROR(__xludf.DUMMYFUNCTION("""COMPUTED_VALUE"""),"DEPARTMENT OF SOCIAL WELFARE & DEVT") -> DEPARTMENT OF SOCIAL WELFARE & DEVT | AM62: =IFERROR(__xludf.DUMMYFUNCTION("""COMPUTED_VALUE"""),"February") -> February | AN62: =IFERROR(__xludf.DUMMYFUNCTION("""COMPUTED_VALUE"""),1.0) -> 1 | AP62: =IFERROR(__xludf.DUMMYFUNCTION("""COMPUTED_VALUE"""),"DEPARTMENT OF SOCIAL WELFARE & DEVT") -> DEPARTMENT OF SOCIAL WELFARE & DEVT | AQ62: =IFERROR(__xludf.DUMMYFUNCTION("""COMPUTED_VALUE"""),"February") -> February | AR62: =IFERROR(__xludf.DUMMYFUNCTION("""COMPUTED_VALUE"""),1.0) -> 1
A63: SO00000566 | B63: 1200006917.00 | C63: EAST WEST BANK - BAJADA 2FLR. | D63: 45308 | E63: 4384.5 | F63: ANGELI SUMINGIT | K63: EAST WEST BANK - BAJADA 2FLR. | L63: January | M63: 4384.5 | AL63: =IFERROR(__xludf.DUMMYFUNCTION("""COMPUTED_VALUE"""),"DEPARTMENT OF SOCIAL WELFARE & DEVT Total") -> DEPARTMENT OF SOCIAL WELFARE & DEVT Total | AN63: =IFERROR(__xludf.DUMMYFUNCTION("""COMPUTED_VALUE"""),1.0) -> 1 | AP63: =IFERROR(__xludf.DUMMYFUNCTION("""COMPUTED_VALUE"""),"DEPARTMENT OF SOCIAL WELFARE & DEVT Total") -> DEPARTMENT OF SOCIAL WELFARE & DEVT Total | AR63: =IFERROR(__xludf.DUMMYFUNCTION("""COMPUTED_VALUE"""),1.0) -> 1
A64: SO00000530 | B64: 1250002653.00 | C64: TRINITAS FOOD CORP. | D64: 45308 | E64: 5596 | F64: ANGELI SUMINGIT | K64: TRINITAS FOOD CORP. | L64: January | M64: 5596 | AL64: =IFERROR(__xludf.DUMMYFUNCTION("""COMPUTED_VALUE"""),"DEPARTMENT OF TOURISM") -> DEPARTMENT OF TOURISM | AM64: =IFERROR(__xludf.DUMMYFUNCTION("""COMPUTED_VALUE"""),"January") -> January | AN64: =IFERROR(__xludf.DUMMYFUNCTION("""COMPUTED_VALUE"""),1.0) -> 1 | AP64: =IFERROR(__xludf.DUMMYFUNCTION("""COMPUTED_VALUE"""),"DEPARTMENT OF TOURISM") -> DEPARTMENT OF TOURISM | AQ64: =IFERROR(__xludf.DUMMYFUNCTION("""COMPUTED_VALUE"""),"January") -> January | AR64: =IFERROR(__xludf.DUMMYFUNCTION("""COMPUTED_VALUE"""),1.0) -> 1
A65: SO00000573 | B65: 1250001178.00 | C65: MOTORMALL DAVAO CORPORATION | D65: 45309 | E65: 3488.5 | F65: ANGELI SUMINGIT | K65: MOTORMALL DAVAO CORPORATION | L65: January | M65: 3488.5 | AL65: =IFERROR(__xludf.DUMMYFUNCTION("""COMPUTED_VALUE"""),"DEPARTMENT OF TOURISM Total") -> DEPARTMENT OF TOURISM Total | AN65: =IFERROR(__xludf.DUMMYFUNCTION("""COMPUTED_VALUE"""),1.0) -> 1 | AP65: =IFERROR(__xludf.DUMMYFUNCTION("""COMPUTED_VALUE"""),"DEPARTMENT OF TOURISM Total") -> DEPARTMENT OF TOURISM Total | AR65: =IFERROR(__xludf.DUMMYFUNCTION("""COMPUTED_VALUE"""),1.0) -> 1
A66: SO00000572 | B66: 1250004411.00 | C66: GREENKREATIONS INC. | D66: 45309 | E66: 5588.5 | F66: ANGELI SUMINGIT | K66: GREENKREATIONS INC. | L66: January | M66: 5588.5 | AL66: =IFERROR(__xludf.DUMMYFUNCTION("""COMPUTED_VALUE"""),"DEPT. OF HUMAN SETTLEMENTS & URBAN DEV'T") -> DEPT. OF HUMAN SETTLEMENTS & URBAN DEV'T | AM66: =IFERROR(__xludf.DUMMYFUNCTION("""COMPUTED_VALUE"""),"January") -> January | AN66: =IFERROR(__xludf.DUMMYFUNCTION("""COMPUTED_VALUE"""),4.0) -> 4 | AP66: =IFERROR(__xludf.DUMMYFUNCTION("""COMPUTED_VALUE"""),"DEPT. OF HUMAN SETTLEMENTS & URBAN DEV'T") -> DEPT. OF HUMAN SETTLEMENTS & URBAN DEV'T | AQ66: =IFERROR(__xludf.DUMMYFUNCTION("""COMPUTED_VALUE"""),"January") -> January | AR66: =IFERROR(__xludf.DUMMYFUNCTION("""COMPUTED_VALUE"""),4.0) -> 4
A67: SO00000589 | B67: 1200007752.00 | C67: INNOBUILDTEK DEVELOPMENT INC | D67: 45309 | E67: 28093.6 | F67: ANGELI SUMINGIT | K67: INNOBUILDTEK DEVELOPMENT INC | L67: January | M67: 28093.6 | AL67: =IFERROR(__xludf.DUMMYFUNCTION("""COMPUTED_VALUE"""),"DEPT. OF HUMAN SETTLEMENTS & URBAN DEV'T Total") -> DEPT. OF HUMAN SETTLEMENTS & URBAN DEV'T Total | AN67: =IFERROR(__xludf.DUMMYFUNCTION("""COMPUTED_VALUE"""),4.0) -> 4 | AP67: =IFERROR(__xludf.DUMMYFUNCTION("""COMPUTED_VALUE"""),"DEPT. OF HUMAN SETTLEMENTS & URBAN DEV'T Total") -> DEPT. OF HUMAN SETTLEMENTS & URBAN DEV'T Total | AR67: =IFERROR(__xludf.DUMMYFUNCTION("""COMPUTED_VALUE"""),4.0) -> 4
A68: SO00000616 | B68: 1220000614.00 | C68: SUNFRESH AGRICULTURAL VENTURES INC. | D68: 45310 | E68: 1762 | F68: ANGELI SUMINGIT | K68: SUNFRESH AGRICULTURAL VENTURES INC. | L68: January | M68: 1762 | AL68: =IFERROR(__xludf.DUMMYFUNCTION("""COMPUTED_VALUE"""),"DEPT. OF TRADE & INDUSTRY- RO-11") -> DEPT. OF TRADE & INDUSTRY- RO-11 | AM68: =IFERROR(__xludf.DUMMYFUNCTION("""COMPUTED_VALUE"""),"January") -> January | AN68: =IFERROR(__xludf.DUMMYFUNCTION("""COMPUTED_VALUE"""),1.0) -> 1 | AP68: =IFERROR(__xludf.DUMMYFUNCTION("""COMPUTED_VALUE"""),"DEPT. OF TRADE & INDUSTRY- RO-11") -> DEPT. OF TRADE & INDUSTRY- RO-11 | AQ68: =IFERROR(__xludf.DUMMYFUNCTION("""COMPUTED_VALUE"""),"January") -> January | AR68: =IFERROR(__xludf.DUMMYFUNCTION("""COMPUTED_VALUE"""),1.0) -> 1
A69: SO00000621 | B69: 1200007686.00 | C69: PHILIPS GLASS & ALUMINUM SALES INC. | D69: 45310 | E69: 4819 | F69: ANGELI SUMINGIT | K69: PHILIPS GLASS & ALUMINUM SALES INC. | L69: January | M69: 4819 | AL69: =IFERROR(__xludf.DUMMYFUNCTION("""COMPUTED_VALUE"""),"DEPT. OF TRADE & INDUSTRY- RO-11 Total") -> DEPT. OF TRADE & INDUSTRY- RO-11 Total | AN69: =IFERROR(__xludf.DUMMYFUNCTION("""COMPUTED_VALUE"""),1.0) -> 1 | AP69: =IFERROR(__xludf.DUMMYFUNCTION("""COMPUTED_VALUE"""),"DEPT. OF TRADE & INDUSTRY- RO-11 Total") -> DEPT. OF TRADE & INDUSTRY- RO-11 Total | AR69: =IFERROR(__xludf.DUMMYFUNCTION("""COMPUTED_VALUE"""),1.0) -> 1
A70: SO00000677 | B70: 1250000164.00 | C70: AKTIV MULTI TRADING CO. PHILS. INC. | D70: 45313 | E70: 779.25 | F70: ANGELI SUMINGIT | K70: AKTIV MULTI TRADING CO. PHILS. INC. | L70: January | M70: 779.25 | AL70: =IFERROR(__xludf.DUMMYFUNCTION("""COMPUTED_VALUE"""),"DIGOS WATER DISTRICT") -> DIGOS WATER DISTRICT | AM70: =IFERROR(__xludf.DUMMYFUNCTION("""COMPUTED_VALUE"""),"February") -> February | AN70: =IFERROR(__xludf.DUMMYFUNCTION("""COMPUTED_VALUE"""),1.0) -> 1 | AP70: =IFERROR(__xludf.DUMMYFUNCTION("""COMPUTED_VALUE"""),"DIGOS WATER DISTRICT") -> DIGOS WATER DISTRICT | AQ70: =IFERROR(__xludf.DUMMYFUNCTION("""COMPUTED_VALUE"""),"February") -> February | AR70: =IFERROR(__xludf.DUMMYFUNCTION("""COMPUTED_VALUE"""),1.0) -> 1
A71: SO00000690 | B71: 1200008786.00 | C71: KILOTRADE | D71: 45313 | E71: 1710.3 | F71: ANGELI SUMINGIT | K71: KILOTRADE | L71: January | M71: 1710.3 | AM71: =IFERROR(__xludf.DUMMYFUNCTION("""COMPUTED_VALUE"""),"January") -> January | AN71: =IFERROR(__xludf.DUMMYFUNCTION("""COMPUTED_VALUE"""),1.0) -> 1 | AQ71: =IFERROR(__xludf.DUMMYFUNCTION("""COMPUTED_VALUE"""),"January") -> January | AR71: =IFERROR(__xludf.DUMMYFUNCTION("""COMPUTED_VALUE"""),1.0) -> 1
A72: SO00000662 | B72: 1200006917.00 | C72: EAST WEST BANK - BAJADA 2FLR. | D72: 45313 | E72: 2200 | F72: ANGELI SUMINGIT | K72: EAST WEST BANK - BAJADA 2FLR. | L72: January | M72: 2200 | AL72: =IFERROR(__xludf.DUMMYFUNCTION("""COMPUTED_VALUE"""),"DIGOS WATER DISTRICT Total") -> DIGOS WATER DISTRICT Total | AN72: =IFERROR(__xludf.DUMMYFUNCTION("""COMPUTED_VALUE"""),2.0) -> 2 | AP72: =IFERROR(__xludf.DUMMYFUNCTION("""COMPUTED_VALUE"""),"DIGOS WATER DISTRICT Total") -> DIGOS WATER DISTRICT Total | AR72: =IFERROR(__xludf.DUMMYFUNCTION("""COMPUTED_VALUE"""),2.0) -> 2
A73: SO00000663 | B73: 1250002653.00 | C73: TRINITAS FOOD CORP. | D73: 45313 | E73: 3251 | F73: ANGELI SUMINGIT | K73: TRINITAS FOOD CORP. | L73: January | M73: 3251 | AL73: =IFERROR(__xludf.DUMMYFUNCTION("""COMPUTED_VALUE"""),"EAST WEST BANK") -> EAST WEST BANK | AM73: =IFERROR(__xludf.DUMMYFUNCTION("""COMPUTED_VALUE"""),"January") -> January | AN73: =IFERROR(__xludf.DUMMYFUNCTION("""COMPUTED_VALUE"""),1.0) -> 1 | AP73: =IFERROR(__xludf.DUMMYFUNCTION("""COMPUTED_VALUE"""),"EAST WEST BANK") -> EAST WEST BANK | AQ73: =IFERROR(__xludf.DUMMYFUNCTION("""COMPUTED_VALUE"""),"January") -> January | AR73: =IFERROR(__xludf.DUMMYFUNCTION("""COMPUTED_VALUE"""),1.0) -> 1
A74: SO00000682 | B74: 1250005019.00 | C74: SEADOVE MARITIME SERVICES INC. | D74: 45313 | E74: 10168 | F74: ANGELI SUMINGIT | K74: SEADOVE MARITIME SERVICES INC. | L74: January | M74: 10168 | AL74: =IFERROR(__xludf.DUMMYFUNCTION("""COMPUTED_VALUE"""),"EAST WEST BANK Total") -> EAST WEST BANK Total | AN74: =IFERROR(__xludf.DUMMYFUNCTION("""COMPUTED_VALUE"""),1.0) -> 1 | AP74: =IFERROR(__xludf.DUMMYFUNCTION("""COMPUTED_VALUE"""),"EAST WEST BANK Total") -> EAST WEST BANK Total | AR74: =IFERROR(__xludf.DUMMYFUNCTION("""COMPUTED_VALUE"""),1.0) -> 1
A75: SO00000684 | B75: 1250005019.00 | C75: SEADOVE MARITIME SERVICES INC. | D75: 45313 | E75: 10316.4 | F75: ANGELI SUMINGIT | K75: SEADOVE MARITIME SERVICES INC. | L75: January | M75: 10316.4 | AL75: =IFERROR(__xludf.DUMMYFUNCTION("""COMPUTED_VALUE"""),"EAST WEST BANK - BAJADA 2FLR.") -> EAST WEST BANK - BAJADA 2FLR. | AM75: =IFERROR(__xludf.DUMMYFUNCTION("""COMPUTED_VALUE"""),"January") -> January | AN75: =IFERROR(__xludf.DUMMYFUNCTION("""COMPUTED_VALUE"""),2.0) -> 2 | AP75: =IFERROR(__xludf.DUMMYFUNCTION("""COMPUTED_VALUE"""),"EAST WEST BANK - BAJADA 2FLR.") -> EAST WEST BANK - BAJADA 2FLR. | AQ75: =IFERROR(__xludf.DUMMYFUNCTION("""COMPUTED_VALUE"""),"January") -> January | AR75: =IFERROR(__xludf.DUMMYFUNCTION("""COMPUTED_VALUE"""),2.0) -> 2
A76: SO00000660 | B76: 1250009576.00 | C76: RBGM MEDICAL EXPRESS SALES INC. | D76: 45313 | E76: 21920 | F76: ANGELI SUMINGIT | K76: RBGM MEDICAL EXPRESS SALES INC. | L76: January | M76: 21920 | AL76: =IFERROR(__xludf.DUMMYFUNCTION("""COMPUTED_VALUE"""),"EAST WEST BANK - BAJADA 2FLR. Total") -> EAST WEST BANK - BAJADA 2FLR. Total | AN76: =IFERROR(__xludf.DUMMYFUNCTION("""COMPUTED_VALUE"""),2.0) -> 2 | AP76: =IFERROR(__xludf.DUMMYFUNCTION("""COMPUTED_VALUE"""),"EAST WEST BANK - BAJADA 2FLR. Total") -> EAST WEST BANK - BAJADA 2FLR. Total | AR76: =IFERROR(__xludf.DUMMYFUNCTION("""COMPUTED_VALUE"""),2.0) -> 2
A77: SO00000692 | B77: 1200007818.00 | C77: DEPT. OF TRADE & INDUSTRY- RO-11 | D77: 45313 | E77: 27978 | F77: GRACE POLPOL | K77: DEPT. OF TRADE & INDUSTRY- RO-11 | L77: January | M77: 27978 | AL77: =IFERROR(__xludf.DUMMYFUNCTION("""COMPUTED_VALUE"""),"EAST WEST BANK - DAVAO AGDAO BRANCH") -> EAST WEST BANK - DAVAO AGDAO BRANCH | AM77: =IFERROR(__xludf.DUMMYFUNCTION("""COMPUTED_VALUE"""),"January") -> January | AN77: =IFERROR(__xludf.DUMMYFUNCTION("""COMPUTED_VALUE"""),1.0) -> 1 | AP77: =IFERROR(__xludf.DUMMYFUNCTION("""COMPUTED_VALUE"""),"EAST WEST BANK - DAVAO AGDAO BRANCH") -> EAST WEST BANK - DAVAO AGDAO BRANCH | AQ77: =IFERROR(__xludf.DUMMYFUNCTION("""COMPUTED_VALUE"""),"January") -> January | AR77: =IFERROR(__xludf.DUMMYFUNCTION("""COMPUTED_VALUE"""),1.0) -> 1
A78: SO00000701 | B78: 1250001764.00 | C78: STENIEL MINDANAO PACKAGING CORPORATION | D78: 45314 | E78: 240 | F78: ANGELI SUMINGIT | K78: STENIEL MINDANAO PACKAGING CORPORATION | L78: January | M78: 240 | AL78: =IFERROR(__xludf.DUMMYFUNCTION("""COMPUTED_VALUE"""),"EAST WEST BANK - DAVAO AGDAO BRANCH Total") -> EAST WEST BANK - DAVAO AGDAO BRANCH Total | AN78: =IFERROR(__xludf.DUMMYFUNCTION("""COMPUTED_VALUE"""),1.0) -> 1 | AP78: =IFERROR(__xludf.DUMMYFUNCTION("""COMPUTED_VALUE"""),"EAST WEST BANK - DAVAO AGDAO BRANCH Total") -> EAST WEST BANK - DAVAO AGDAO BRANCH Total | AR78: =IFERROR(__xludf.DUMMYFUNCTION("""COMPUTED_VALUE"""),1.0) -> 1
A79: SO00000730 | B79: 1250010352.00 | C79: FIESTA APPLIANCE CENTER INC. | D79: 45314 | E79: 799 | F79: Vivian Chavez | K79: FIESTA APPLIANCE CENTER INC. | L79: January | M79: 799 | AL79: =IFERROR(__xludf.DUMMYFUNCTION("""COMPUTED_VALUE"""),"EC GONZAGA ENTERPRISES") -> EC GONZAGA ENTERPRISES | AM79: =IFERROR(__xludf.DUMMYFUNCTION("""COMPUTED_VALUE"""),"February") -> February | AN79: =IFERROR(__xludf.DUMMYFUNCTION("""COMPUTED_VALUE"""),4.0) -> 4 | AP79: =IFERROR(__xludf.DUMMYFUNCTION("""COMPUTED_VALUE"""),"EC GONZAGA ENTERPRISES") -> EC GONZAGA ENTERPRISES | AQ79: =IFERROR(__xludf.DUMMYFUNCTION("""COMPUTED_VALUE"""),"February") -> February | AR79: =IFERROR(__xludf.DUMMYFUNCTION("""COMPUTED_VALUE"""),4.0) -> 4
A80: SO00000702 | B80: 1250001276.00 | C80: PHILIPPINE COCONUT AUTHORITY-REG.XI | D80: 45314 | E80: 1316 | F80: GRACE POLPOL | K80: PHILIPPINE COCONUT AUTHORITY-REG.XI | L80: January | M80: 1316 | AM80: =IFERROR(__xludf.DUMMYFUNCTION("""COMPUTED_VALUE"""),"January") -> January | AN80: =IFERROR(__xludf.DUMMYFUNCTION("""COMPUTED_VALUE"""),2.0) -> 2 | AQ80: =IFERROR(__xludf.DUMMYFUNCTION("""COMPUTED_VALUE"""),"January") -> January | AR80: =IFERROR(__xludf.DUMMYFUNCTION("""COMPUTED_VALUE"""),2.0) -> 2
A81: SO00000707 | B81: 1250001764.00 | C81: STENIEL MINDANAO PACKAGING CORPORATION | D81: 45314 | E81: 2122 | F81: ANGELI SUMINGIT | K81: STENIEL MINDANAO PACKAGING CORPORATION | L81: January | M81: 2122 | AL81: =IFERROR(__xludf.DUMMYFUNCTION("""COMPUTED_VALUE"""),"EC GONZAGA ENTERPRISES Total") -> EC GONZAGA ENTERPRISES Total | AN81: =IFERROR(__xludf.DUMMYFUNCTION("""COMPUTED_VALUE"""),6.0) -> 6 | AP81: =IFERROR(__xludf.DUMMYFUNCTION("""COMPUTED_VALUE"""),"EC GONZAGA ENTERPRISES Total") -> EC GONZAGA ENTERPRISES Total | AR81: =IFERROR(__xludf.DUMMYFUNCTION("""COMPUTED_VALUE"""),6.0) -> 6
A82: SO00000735 | B82: 1200008869.00 | C82: GTM GET THINGS MOVING DISTRIBUTION INC. | D82: 45314 | E82: 2485.85 | F82: ANGELI SUMINGIT | K82: GTM GET THINGS MOVING DISTRIBUTION INC. | L82: January | M82: 2485.85 | AL82: =IFERROR(__xludf.DUMMYFUNCTION("""COMPUTED_VALUE"""),"EHB ENTERPRISES & PRINTHAUS") -> EHB ENTERPRISES & PRINTHAUS | AM82: =IFERROR(__xludf.DUMMYFUNCTION("""COMPUTED_VALUE"""),"January") -> January | AN82: =IFERROR(__xludf.DUMMYFUNCTION("""COMPUTED_VALUE"""),1.0) -> 1 | AP82: =IFERROR(__xludf.DUMMYFUNCTION("""COMPUTED_VALUE"""),"EHB ENTERPRISES & PRINTHAUS") -> EHB ENTERPRISES & PRINTHAUS | AQ82: =IFERROR(__xludf.DUMMYFUNCTION("""COMPUTED_VALUE"""),"January") -> January | AR82: =IFERROR(__xludf.DUMMYFUNCTION("""COMPUTED_VALUE"""),1.0) -> 1
A83: SO00000717 | B83: 1200008243.00 | C83: EAST WEST BANK - DAVAO AGDAO BRANCH | D83: 45314 | E83: 7782.5 | F83: ANGELI SUMINGIT | K83: EAST WEST BANK - DAVAO AGDAO BRANCH | L83: January | M83: 7782.5 | AL83: =IFERROR(__xludf.DUMMYFUNCTION("""COMPUTED_VALUE"""),"EHB ENTERPRISES & PRINTHAUS Total") -> EHB ENTERPRISES & PRINTHAUS Total | AN83: =IFERROR(__xludf.DUMMYFUNCTION("""COMPUTED_VALUE"""),1.0) -> 1 | AP83: =IFERROR(__xludf.DUMMYFUNCTION("""COMPUTED_VALUE"""),"EHB ENTERPRISES & PRINTHAUS Total") -> EHB ENTERPRISES & PRINTHAUS Total | AR83: =IFERROR(__xludf.DUMMYFUNCTION("""COMPUTED_VALUE"""),1.0) -> 1
A84: SO00000709 | B84: 1250009576.00 | C84: RBGM MEDICAL EXPRESS SALES INC. | D84: 45314 | E84: 13562.7 | F84: ANGELI SUMINGIT | K84: RBGM MEDICAL EXPRESS SALES INC. | L84: January | M84: 13562.7 | AL84: =IFERROR(__xludf.DUMMYFUNCTION("""COMPUTED_VALUE"""),"EQUINOX SYNERGY OPC") -> EQUINOX SYNERGY OPC | AM84: =IFERROR(__xludf.DUMMYFUNCTION("""COMPUTED_VALUE"""),"January") -> January | AN84: =IFERROR(__xludf.DUMMYFUNCTION("""COMPUTED_VALUE"""),2.0) -> 2 | AP84: =IFERROR(__xludf.DUMMYFUNCTION("""COMPUTED_VALUE"""),"EQUINOX SYNERGY OPC") -> EQUINOX SYNERGY OPC | AQ84: =IFERROR(__xludf.DUMMYFUNCTION("""COMPUTED_VALUE"""),"January") -> January | AR84: =IFERROR(__xludf.DUMMYFUNCTION("""COMPUTED_VALUE"""),2.0) -> 2
A85: SO00000728 | B85: 1250001142.00 | C85: DEPT. OF HUMAN SETTLEMENTS & URBAN DEV'T | D85: 45314 | E85: 16200 | F85: GRACE POLPOL | K85: DEPT. OF HUMAN SETTLEMENTS & URBAN DEV'T | L85: January | M85: 16200 | AL85: =IFERROR(__xludf.DUMMYFUNCTION("""COMPUTED_VALUE"""),"EQUINOX SYNERGY OPC Total") -> EQUINOX SYNERGY OPC Total | AN85: =IFERROR(__xludf.DUMMYFUNCTION("""COMPUTED_VALUE"""),2.0) -> 2 | AP85: =IFERROR(__xludf.DUMMYFUNCTION("""COMPUTED_VALUE"""),"EQUINOX SYNERGY OPC Total") -> EQUINOX SYNERGY OPC Total | AR85: =IFERROR(__xludf.DUMMYFUNCTION("""COMPUTED_VALUE"""),2.0) -> 2
A86: SO00000723 | B86: 1250002423.00 | C86: LAND BANK OF THE PHILIPPINES - MATI BRANCH | D86: 45314 | E86: 33650 | F86: GRACE POLPOL | K86: LAND BANK OF THE PHILIPPINES - MATI BRANCH | L86: January | M86: 33650 | AL86: =IFERROR(__xludf.DUMMYFUNCTION("""COMPUTED_VALUE"""),"EZGAB CORPORATION") -> EZGAB CORPORATION | AM86: =IFERROR(__xludf.DUMMYFUNCTION("""COMPUTED_VALUE"""),"January") -> January | AN86: =IFERROR(__xludf.DUMMYFUNCTION("""COMPUTED_VALUE"""),2.0) -> 2 | AP86: =IFERROR(__xludf.DUMMYFUNCTION("""COMPUTED_VALUE"""),"EZGAB CORPORATION") -> EZGAB CORPORATION | AQ86: =IFERROR(__xludf.DUMMYFUNCTION("""COMPUTED_VALUE"""),"January") -> January | AR86: =IFERROR(__xludf.DUMMYFUNCTION("""COMPUTED_VALUE"""),2.0) -> 2
A87: SO00000729 | B87: 1250001142.00 | C87: DEPT. OF HUMAN SETTLEMENTS & URBAN DEV'T | D87: 45314 | E87: 47250 | F87: GRACE POLPOL | K87: DEPT. OF HUMAN SETTLEMENTS & URBAN DEV'T | L87: January | M87: 47250 | AL87: =IFERROR(__xludf.DUMMYFUNCTION("""COMPUTED_VALUE"""),"EZGAB CORPORATION Total") -> EZGAB CORPORATION Total | AN87: =IFERROR(__xludf.DUMMYFUNCTION("""COMPUTED_VALUE"""),2.0) -> 2 | AP87: =IFERROR(__xludf.DUMMYFUNCTION("""COMPUTED_VALUE"""),"EZGAB CORPORATION Total") -> EZGAB CORPORATION Total | AR87: =IFERROR(__xludf.DUMMYFUNCTION("""COMPUTED_VALUE"""),2.0) -> 2
A88: SO00000739 | B88: 1250001764.00 | C88: STENIEL MINDANAO PACKAGING CORPORATION | D88: 45314 | E88: 105000 | F88: ANGELI SUMINGIT | K88: STENIEL MINDANAO PACKAGING CORPORATION | L88: January | M88: 105000 | AL88: =IFERROR(__xludf.DUMMYFUNCTION("""COMPUTED_VALUE"""),"F.S. DIZON & SONS INC.") -> F.S. DIZON & SONS INC. | AM88: =IFERROR(__xludf.DUMMYFUNCTION("""COMPUTED_VALUE"""),"February") -> February | AN88: =IFERROR(__xludf.DUMMYFUNCTION("""COMPUTED_VALUE"""),1.0) -> 1 | AP88: =IFERROR(__xludf.DUMMYFUNCTION("""COMPUTED_VALUE"""),"F.S. DIZON & SONS INC.") -> F.S. DIZON & SONS INC. | AQ88: =IFERROR(__xludf.DUMMYFUNCTION("""COMPUTED_VALUE"""),"February") -> February | AR88: =IFERROR(__xludf.DUMMYFUNCTION("""COMPUTED_VALUE"""),1.0) -> 1
A89: SO00000750 | B89: 1250000438.00 | C89: CIVIL SERVICE COMMISSION-REG. XI | D89: 45315 | E89: 1048 | F89: GRACE POLPOL | K89: CIVIL SERVICE COMMISSION-REG. XI | L89: January | M89: 1048 | AL89: =IFERROR(__xludf.DUMMYFUNCTION("""COMPUTED_VALUE"""),"F.S. DIZON & SONS INC. Total") -> F.S. DIZON & SONS INC. Total | AN89: =IFERROR(__xludf.DUMMYFUNCTION("""COMPUTED_VALUE"""),1.0) -> 1 | AP89: =IFERROR(__xludf.DUMMYFUNCTION("""COMPUTED_VALUE"""),"F.S. DIZON & SONS INC. Total") -> F.S. DIZON & SONS INC. Total | AR89: =IFERROR(__xludf.DUMMYFUNCTION("""COMPUTED_VALUE"""),1.0) -> 1
A90: SO00000759 | B90: 1250000147.00 | C90: MALAYAN INSURANCE COMPANY INC. | D90: 45315 | E90: 1100 | F90: ANGELI SUMINGIT | K90: MALAYAN INSURANCE COMPANY INC. | L90: January | M90: 1100 | AL90: =IFERROR(__xludf.DUMMYFUNCTION("""COMPUTED_VALUE"""),"FAR EAST ASSOCIATES") -> FAR EAST ASSOCIATES | AM90: =IFERROR(__xludf.DUMMYFUNCTION("""COMPUTED_VALUE"""),"February") -> February | AN90: =IFERROR(__xludf.DUMMYFUNCTION("""COMPUTED_VALUE"""),1.0) -> 1 | AP90: =IFERROR(__xludf.DUMMYFUNCTION("""COMPUTED_VALUE"""),"FAR EAST ASSOCIATES") -> FAR EAST ASSOCIATES | AQ90: =IFERROR(__xludf.DUMMYFUNCTION("""COMPUTED_VALUE"""),"February") -> February | AR90: =IFERROR(__xludf.DUMMYFUNCTION("""COMPUTED_VALUE"""),1.0) -> 1
A91: SO00000758 | B91: 1200007752.00 | C91: INNOBUILDTEK DEVELOPMENT INC | D91: 45315 | E91: 1686 | F91: ANGELI SUMINGIT | K91: INNOBUILDTEK DEVELOPMENT INC | L91: January | M91: 1686 | AM91: =IFERROR(__xludf.DUMMYFUNCTION("""COMPUTED_VALUE"""),"January") -> January | AN91: =IFERROR(__xludf.DUMMYFUNCTION("""COMPUTED_VALUE"""),1.0) -> 1 | AQ91: =IFERROR(__xludf.DUMMYFUNCTION("""COMPUTED_VALUE"""),"January") -> January | AR91: =IFERROR(__xludf.DUMMYFUNCTION("""COMPUTED_VALUE"""),1.0) -> 1
A92: SO00000788 | B92: 1250000629.00 | C92: NATIONAL POLICE COMMISSION | D92: 45315 | E92: 4562 | F92: GRACE POLPOL | K92: NATIONAL POLICE COMMISSION | L92: January | M92: 4562 | AL92: =IFERROR(__xludf.DUMMYFUNCTION("""COMPUTED_VALUE"""),"FAR EAST ASSOCIATES Total") -> FAR EAST ASSOCIATES Total | AN92: =IFERROR(__xludf.DUMMYFUNCTION("""COMPUTED_VALUE"""),2.0) -> 2 | AP92: =IFERROR(__xludf.DUMMYFUNCTION("""COMPUTED_VALUE"""),"FAR EAST ASSOCIATES Total") -> FAR EAST ASSOCIATES Total | AR92: =IFERROR(__xludf.DUMMYFUNCTION("""COMPUTED_VALUE"""),2.0) -> 2
A93: SO00000789 | B93: 1250000629.00 | C93: NATIONAL POLICE COMMISSION | D93: 45315 | E93: 4700 | F93: GRACE POLPOL | K93: NATIONAL POLICE COMMISSION | L93: January | M93: 4700 | AL93: =IFERROR(__xludf.DUMMYFUNCTION("""COMPUTED_VALUE"""),"FELY M. MORATA CUSTOM BROKERAGE SERVICES") -> FELY M. MORATA CUSTOM BROKERAGE SERVICES | AM93: =IFERROR(__xludf.DUMMYFUNCTION("""COMPUTED_VALUE"""),"January") -> January | AN93: =IFERROR(__xludf.DUMMYFUNCTION("""COMPUTED_VALUE"""),1.0) -> 1 | AP93: =IFERROR(__xludf.DUMMYFUNCTION("""COMPUTED_VALUE"""),"FELY M. MORATA CUSTOM BROKERAGE SERVICES") -> FELY M. MORATA CUSTOM BROKERAGE SERVICES | AQ93: =IFERROR(__xludf.DUMMYFUNCTION("""COMPUTED_VALUE"""),"January") -> January | AR93: =IFERROR(__xludf.DUMMYFUNCTION("""COMPUTED_VALUE"""),1.0) -> 1
A94: SO00000755 | B94: 1250000438.00 | C94: CIVIL SERVICE COMMISSION-REG. XI | D94: 45315 | E94: 11901.4 | F94: GRACE POLPOL | K94: CIVIL SERVICE COMMISSION-REG. XI | L94: January | M94: 11901.4 | AL94: =IFERROR(__xludf.DUMMYFUNCTION("""COMPUTED_VALUE"""),"FELY M. MORATA CUSTOM BROKERAGE SERVICES Total") -> FELY M. MORATA CUSTOM BROKERAGE SERVICES Total | AN94: =IFERROR(__xludf.DUMMYFUNCTION("""COMPUTED_VALUE"""),1.0) -> 1 | AP94: =IFERROR(__xludf.DUMMYFUNCTION("""COMPUTED_VALUE"""),"FELY M. MORATA CUSTOM BROKERAGE SERVICES Total") -> FELY M. MORATA CUSTOM BROKERAGE SERVICES Total | AR94: =IFERROR(__xludf.DUMMYFUNCTION("""COMPUTED_VALUE"""),1.0) -> 1
A95: SO00000801 | B95: 1250000255.00 | C95: DEPARTMENT OF TOURISM | D95: 45315 | E95: 12300 | F95: GRACE POLPOL | K95: DEPARTMENT OF TOURISM | L95: January | M95: 12300 | AL95: =IFERROR(__xludf.DUMMYFUNCTION("""COMPUTED_VALUE"""),"FIESTA APPLIANCE CENTER INC.") -> FIESTA APPLIANCE CENTER INC. | AM95: =IFERROR(__xludf.DUMMYFUNCTION("""COMPUTED_VALUE"""),"January") -> January | AN95: =IFERROR(__xludf.DUMMYFUNCTION("""COMPUTED_VALUE"""),1.0) -> 1 | AP95: =IFERROR(__xludf.DUMMYFUNCTION("""COMPUTED_VALUE"""),"FIESTA APPLIANCE CENTER INC.") -> FIESTA APPLIANCE CENTER INC. | AQ95: =IFERROR(__xludf.DUMMYFUNCTION("""COMPUTED_VALUE"""),"January") -> January | AR95: =IFERROR(__xludf.DUMMYFUNCTION("""COMPUTED_VALUE"""),1.0) -> 1
A96: SO00000803 | B96: 1250003683.00 | C96: JATHNIER CORPORATION | D96: 45315 | E96: 13000 | F96: ANGELI SUMINGIT | K96: JATHNIER CORPORATION | L96: January | M96: 13000 | AL96: =IFERROR(__xludf.DUMMYFUNCTION("""COMPUTED_VALUE"""),"FIESTA APPLIANCE CENTER INC. Total") -> FIESTA APPLIANCE CENTER INC. Total | AN96: =IFERROR(__xludf.DUMMYFUNCTION("""COMPUTED_VALUE"""),1.0) -> 1 | AP96: =IFERROR(__xludf.DUMMYFUNCTION("""COMPUTED_VALUE"""),"FIESTA APPLIANCE CENTER INC. Total") -> FIESTA APPLIANCE CENTER INC. Total | AR96: =IFERROR(__xludf.DUMMYFUNCTION("""COMPUTED_VALUE"""),1.0) -> 1
A97: SO00000754 | B97: 1250000438.00 | C97: CIVIL SERVICE COMMISSION-REG. XI | D97: 45315 | E97: 16466 | F97: GRACE POLPOL | K97: CIVIL SERVICE COMMISSION-REG. XI | L97: January | M97: 16466 | AL97: =IFERROR(__xludf.DUMMYFUNCTION("""COMPUTED_VALUE"""),"FOCUSINC GROUP CORP.") -> FOCUSINC GROUP CORP. | AM97: =IFERROR(__xludf.DUMMYFUNCTION("""COMPUTED_VALUE"""),"January") -> January | AN97: =IFERROR(__xludf.DUMMYFUNCTION("""COMPUTED_VALUE"""),1.0) -> 1 | AP97: =IFERROR(__xludf.DUMMYFUNCTION("""COMPUTED_VALUE"""),"FOCUSINC GROUP CORP.") -> FOCUSINC GROUP CORP. | AQ97: =IFERROR(__xludf.DUMMYFUNCTION("""COMPUTED_VALUE"""),"January") -> January | AR97: =IFERROR(__xludf.DUMMYFUNCTION("""COMPUTED_VALUE"""),1.0) -> 1
A98: SO00000752 | B98: 1250000438.00 | C98: CIVIL SERVICE COMMISSION-REG. XI | D98: 45315 | E98: 18387.75 | F98: GRACE POLPOL | K98: CIVIL SERVICE COMMISSION-REG. XI | L98: January | M98: 18387.75 | AL98: =IFERROR(__xludf.DUMMYFUNCTION("""COMPUTED_VALUE"""),"FOCUSINC GROUP CORP. Total") -> FOCUSINC GROUP CORP. Total | AN98: =IFERROR(__xludf.DUMMYFUNCTION("""COMPUTED_VALUE"""),1.0) -> 1 | AP98: =IFERROR(__xludf.DUMMYFUNCTION("""COMPUTED_VALUE"""),"FOCUSINC GROUP CORP. Total") -> FOCUSINC GROUP CORP. Total | AR98: =IFERROR(__xludf.DUMMYFUNCTION("""COMPUTED_VALUE"""),1.0) -> 1
A99: SO00000814 | B99: 1250002297.00 | C99: LAND BANK OF THE PHILS.-BANSALAN BRANCH | D99: 45316 | E99: 966 | F99: GRACE POLPOL | K99: LAND BANK OF THE PHILS.-BANSALAN BRANCH | L99: January | M99: 966 | AL99: =IFERROR(__xludf.DUMMYFUNCTION("""COMPUTED_VALUE"""),"GOLDEN BALES CORPORATION") -> GOLDEN BALES CORPORATION | AM99: =IFERROR(__xludf.DUMMYFUNCTION("""COMPUTED_VALUE"""),"January") -> January | AN99: =IFERROR(__xludf.DUMMYFUNCTION("""COMPUTED_VALUE"""),1.0) -> 1 | AP99: =IFERROR(__xludf.DUMMYFUNCTION("""COMPUTED_VALUE"""),"GOLDEN BALES CORPORATION") -> GOLDEN BALES CORPORATION | AQ99: =IFERROR(__xludf.DUMMYFUNCTION("""COMPUTED_VALUE"""),"January") -> January | AR99: =IFERROR(__xludf.DUMMYFUNCTION("""COMPUTED_VALUE"""),1.0) -> 1
A100: SO00000835 | B100: 1200008027.00 | C100: B.P.I. - LANANG | D100: 45316 | E100: 2200 | F100: ANGELI SUMINGIT | K100: B.P.I. - LANANG | L100: January | M100: 2200 | AL100: =IFERROR(__xludf.DUMMYFUNCTION("""COMPUTED_VALUE"""),"GOLDEN BALES CORPORATION Total") -> GOLDEN BALES CORPORATION Total | AN100: =IFERROR(__xludf.DUMMYFUNCTION("""COMPUTED_VALUE"""),1.0) -> 1 | AP100: =IFERROR(__xludf.DUMMYFUNCTION("""COMPUTED_VALUE"""),"GOLDEN BALES CORPORATION Total") -> GOLDEN BALES CORPORATION Total | AR100: =IFERROR(__xludf.DUMMYFUNCTION("""COMPUTED_VALUE"""),1.0) -> 1
...

Sheet John 2
A1: OrderNbr | B1: Customer | C1: CustomerName | D1: Date | E1: OrderTotal | F1: CreatedBy
A2: SO00000687 | B2: 1250000116 | C2: CITY GOVERNMENT OF DAVAO | D2: 45250 | E2: ₱4372.25 | F2: GRACE POLPOL
A3: SO00000012 | B3: 1250000505 | C3: STAR PAPER CORPORATION | D3: 45294 | E3: ₱1362.00 | F3: ANGELI SUMINGIT
A4: SO00000005 | B4: 1250001764 | C4: STENIEL MINDANAO PACKAGING CORPORATION | D4: 45294 | E4: ₱1500.00 | F4: ANGELI SUMINGIT
A5: SO00000028 | B5: 1250001496 | C5: COMFAC CORPORATION | D5: 45294 | E5: ₱1916.00 | F5: ANGELI SUMINGIT
A6: SO00000021 | B6: 1200006565 | C6: NXTGEN TECHNOLOGIES INC | D6: 45294 | E6: ₱2148.80 | F6: ANGELI SUMINGIT
A7: SO00000026 | B7: 1250004966 | C7: INFIMAX HEALTH PRODUCTS | D7: 45294 | E7: ₱2365.80 | F7: ANGELI SUMINGIT
A8: SO00000020 | B8: 1250001764 | C8: STENIEL MINDANAO PACKAGING CORPORATION | D8: 45294 | E8: ₱2367.50 | F8: ANGELI SUMINGIT
A9: SO00000013 | B9: 1250001142 | C9: DEPT. OF HUMAN SETTLEMENTS & URBAN DEV'T | D9: 45294 | E9: ₱38256.00 | F9: GRACE POLPOL
A10: SO00000097 | B10: 1200006417 | C10: PHIL.FIBER INDUSTRY DEV'T AUTHORITY | D10: 45295 | E10: ₱1500.00 | F10: GRACE POLPOL
A11: SO00000071 | B11: 1250010315 | C11: HI5 SOLUTIONS OPC | D11: 45295 | E11: ₱1600.00 | F11: ANGELI SUMINGIT
A12: SO00000096 | B12: 1250004938 | C12: B.P.I. - BAJADA (FRONTING CONPINCO) | D12: 45295 | E12: ₱4762.10 | F12: ANGELI SUMINGIT
A13: SO00000070 | B13: 1250003997 | C13: INSULAR OIL CORPORATION | D13: 45295 | E13: ₱5265.00 | F13: ANGELI SUMINGIT
... A201: SO00001324 | B201: 1250001273 | C201: MILLENNIUM SPECIALTY COCO PRODUCTSINC. | D201: 45337 | E201: ₱1200.00 | F201: ANGELI SUMINGIT

Sheet Johnreyexel

Sheet johnreyexcl
A1: OrderNbr | B1: Customer | C1: CustomerName | D1: Date | E1: OrderTotal | F1: CreatedBy
A2: SO00000687 | B2: 1250000116 | C2: CITY GOVERNMENT OF DAVAO | D2: 45250 | E2: ₱4372.25 | F2: GRACE POLPOL
A3: SO00000012 | B3: 1250000505 | C3: STAR PAPER CORPORATION | D3: 45294 | E3: ₱1362.00 | F3: ANGELI SUMINGIT
A4: SO00000005 | B4: 1250001764 | C4: STENIEL MINDANAO PACKAGING CORPORATION | D4: 45294 | E4: ₱1500.00 | F4: ANGELI SUMINGIT
A5: SO00000028 | B5: 1250001496 | C5: COMFAC CORPORATION | D5: 45294 | E5: ₱1916.00 | F5: ANGELI SUMINGIT
A6: SO00000021 | B6: 1200006565 | C6: NXTGEN TECHNOLOGIES INC | D6: 45294 | E6: ₱2148.80 | F6: ANGELI SUMINGIT
A7: SO00000026 | B7: 1250004966 | C7: INFIMAX HEALTH PRODUCTS | D7: 45294 | E7: ₱2365.80 | F7: ANGELI SUMINGIT
A8: SO00000020 | B8: 1250001764 | C8: STENIEL MINDANAO PACKAGING CORPORATION | D8: 45294 | E8: ₱2367.50 | F8: ANGELI SUMINGIT
A9: SO00000013 | B9: 1250001142 | C9: DEPT. OF HUMAN SETTLEMENTS & URBAN DEV'T | D9: 45294 | E9: ₱38256.00 | F9: GRACE POLPOL
A10: SO00000097 | B10: 1200006417 | C10: PHIL.FIBER INDUSTRY DEV'T AUTHORITY | D10: 45295 | E10: ₱1500.00 | F10: GRACE POLPOL
A11: SO00000071 | B11: 1250010315 | C11: HI5 SOLUTIONS OPC | D11: 45295 | E11: ₱1600.00 | F11: ANGELI SUMINGIT
A12: SO00000096 | B12: 1250004938 | C12: B.P.I. - BAJADA (FRONTING CONPINCO) | D12: 45295 | E12: ₱4762.10 | F12: ANGELI SUMINGIT
A13: SO00000070 | B13: 1250003997 | C13: INSULAR OIL CORPORATION | D13: 45295 | E13: ₱5265.00 | F13: ANGELI SUMINGIT
... A201: SO00001324 | B201: 1250001273 | C201: MILLENNIUM SPECIALTY COCO PRODUCTSINC. | D201: 45337 | E201: ₱1200.00 | F201: ANGELI SUMINGIT

Sheet Pivot Table 2
